{"analyses":[{"domains":["default_domain"],"likelihood":"simPdf_asimovData","name":"simPdf_asimovData","parameters_of_interest":["SigXsecOverSM"]},{"domains":["default_domain"],"likelihood":"simPdf_obsData","name":"simPdf_obsData","parameters_of_interest":["SigXsecOverSM"]}],"data":[{"axes":[{"name":"obs_x_CR_ExtCo_2lSS0tau_Nevt","nbins":1,"value":0.5}],"entries":[],"name":"asimovData_CR_ExtCo_2lSS0tau_Nevt","type":"unbinned","weights":[]},{"axes":[{"name":"obs_x_CR_ExtCo_3l0tau_Nevt","nbins":1,"value":0.5}],"entries":[],"name":"asimovData_CR_ExtCo_3l0tau_Nevt","type":"unbinned","weights":[]},{"axes":[{"name":"obs_x_CR_HFe_2lSS0tau_neg_HT_lep","nbins":3,"value":2.5}],"entries":[],"name":"asimovData_CR_HFe_2lSS0tau_neg_HT_lep","type":"unbinned","weights":[]},{"axes":[{"name":"obs_x_CR_HFe_2lSS0tau_pos_HT_lep","nbins":3,"value":2.5}],"entries":[],"name":"asimovData_CR_HFe_2lSS0tau_pos_HT_lep","type":"unbinned","weights":[]},{"axes":[{"name":"obs_x_CR_HFmu_2lSS0tau_neg_HT_lep","nbins":3,"value":2.5}],"entries":[],"name":"asimovData_CR_HFmu_2lSS0tau_neg_HT_lep","type":"unbinned","weights":[]},{"axes":[{"name":"obs_x_CR_HFmu_2lSS0tau_pos_HT_lep","nbins":3,"value":2.5}],"entries":[],"name":"asimovData_CR_HFmu_2lSS0tau_pos_HT_lep","type":"unbinned","weights":[]},{"axes":[{"name":"obs_x_CR_IntCo_2lSS0tau_Nevt","nbins":1,"value":0.5}],"entries":[],"name":"asimovData_CR_IntCo_2lSS0tau_Nevt","type":"unbinned","weights":[]},{"axes":[{"name":"obs_x_CR_IntCo_3l0tau_Nevt","nbins":1,"value":0.5}],"entries":[],"name":"asimovData_CR_IntCo_3l0tau_Nevt","type":"unbinned","weights":[]},{"axes":[{"name":"obs_x_CR_LowMeff_ttbar_1l1tau_OS","nbins":1,"value":0.5}],"entries":[],"name":"asimovData_CR_LowMeff_ttbar_1l1tau_OS","type":"unbinned","weights":[]},{"axes":[{"name":"obs_x_CR_LowMeff_ttbar_1l1tau_SS","nbins":1,"value":0.5}],"entries":[],"name":"asimovData_CR_LowMeff_ttbar_1l1tau_SS","type":"unbinned","weights":[]},{"axes":[{"name":"obs_x_CR_LowMeff_ttbar_1l2tau","nbins":1,"value":0.5}],"entries":[],"name":"asimovData_CR_LowMeff_ttbar_1l2tau","type":"unbinned","weights":[]},{"axes":[{"name":"obs_x_CR_VV_3l0tau_2or3j_HT_lep","nbins":4,"value":3.5}],"entries":[],"name":"asimovData_CR_VV_3l0tau_2or3j_HT_lep","type":"unbinned","weights":[]},{"axes":[{"name":"obs_x_CR_ttW_2lSS0tau_neg_HT_lep","nbins":3,"value":2.5}],"entries":[],"name":"asimovData_CR_ttW_2lSS0tau_neg_HT_lep","type":"unbinned","weights":[]},{"axes":[{"name":"obs_x_CR_ttW_2lSS0tau_pos_HT_lep","nbins":3,"value":2.5}],"entries":[],"name":"asimovData_CR_ttW_2lSS0tau_pos_HT_lep","type":"unbinned","weights":[]},{"axes":[{"name":"obs_x_CR_ttZ_3l0tau_njets4_HT_lep","nbins":4,"value":3.5}],"entries":[],"name":"asimovData_CR_ttZ_3l0tau_njets4_HT_lep","type":"unbinned","weights":[]},{"axes":[{"name":"obs_x_SR_1l1tau_OS","nbins":5,"value":4.5}],"entries":[],"name":"asimovData_SR_1l1tau_OS","type":"unbinned","weights":[]},{"axes":[{"name":"obs_x_SR_1l1tau_SS","nbins":4,"value":3.5}],"entries":[],"name":"asimovData_SR_1l1tau_SS","type":"unbinned","weights":[]},{"axes":[{"name":"obs_x_SR_1l2tau","nbins":4,"value":3.5}],"entries":[],"name":"asimovData_SR_1l2tau","type":"unbinned","weights":[]},{"axes":[{"name":"obs_x_SR_2lOS1tau_Meff","nbins":5,"value":4.5}],"entries":[],"name":"asimovData_SR_2lOS1tau_Meff","type":"unbinned","weights":[]},{"axes":[{"name":"obs_x_SR_2lOS2tau_Meff","nbins":3,"value":2.5}],"entries":[],"name":"asimovData_SR_2lOS2tau_Meff","type":"unbinned","weights":[]},{"axes":[{"name":"obs_x_SR_2lSSor3l1tau_tauPt125_Meff","nbins":3,"value":2.5}],"entries":[],"name":"asimovData_SR_2lSSor3l1tau_tauPt125_Meff","type":"unbinned","weights":[]},{"axes":[{"name":"obs_x_SR_2lSSor3l1tau_tauPt225_Meff","nbins":3,"value":2.5}],"entries":[],"name":"asimovData_SR_2lSSor3l1tau_tauPt225_Meff","type":"unbinned","weights":[]},{"axes":[{"max":1.0,"min":0.0,"name":"obs_x_CR_ExtCo_2lSS0tau_Nevt","nbins":1}],"contents":[82],"name":"obsData_CR_ExtCo_2lSS0tau_Nevt","type":"binned"},{"axes":[{"max":1.0,"min":0.0,"name":"obs_x_CR_ExtCo_3l0tau_Nevt","nbins":1}],"contents":[8],"name":"obsData_CR_ExtCo_3l0tau_Nevt","type":"binned"},{"axes":[{"max":3.0,"min":0.0,"name":"obs_x_CR_HFe_2lSS0tau_neg_HT_lep","nbins":3}],"contents":[124,76,54],"name":"obsData_CR_HFe_2lSS0tau_neg_HT_lep","type":"binned"},{"axes":[{"max":3.0,"min":0.0,"name":"obs_x_CR_HFe_2lSS0tau_pos_HT_lep","nbins":3}],"contents":[143,133,72],"name":"obsData_CR_HFe_2lSS0tau_pos_HT_lep","type":"binned"},{"axes":[{"max":3.0,"min":0.0,"name":"obs_x_CR_HFmu_2lSS0tau_neg_HT_lep","nbins":3}],"contents":[217,124,74],"name":"obsData_CR_HFmu_2lSS0tau_neg_HT_lep","type":"binned"},{"axes":[{"max":3.0,"min":0.0,"name":"obs_x_CR_HFmu_2lSS0tau_pos_HT_lep","nbins":3}],"contents":[285,181,82],"name":"obsData_CR_HFmu_2lSS0tau_pos_HT_lep","type":"binned"},{"axes":[{"max":1.0,"min":0.0,"name":"obs_x_CR_IntCo_2lSS0tau_Nevt","nbins":1}],"contents":[43],"name":"obsData_CR_IntCo_2lSS0tau_Nevt","type":"binned"},{"axes":[{"max":1.0,"min":0.0,"name":"obs_x_CR_IntCo_3l0tau_Nevt","nbins":1}],"contents":[5],"name":"obsData_CR_IntCo_3l0tau_Nevt","type":"binned"},{"axes":[{"max":1.0,"min":0.0,"name":"obs_x_CR_LowMeff_ttbar_1l1tau_OS","nbins":1}],"contents":[13041],"name":"obsData_CR_LowMeff_ttbar_1l1tau_OS","type":"binned"},{"axes":[{"max":1.0,"min":0.0,"name":"obs_x_CR_LowMeff_ttbar_1l1tau_SS","nbins":1}],"contents":[1162],"name":"obsData_CR_LowMeff_ttbar_1l1tau_SS","type":"binned"},{"axes":[{"max":1.0,"min":0.0,"name":"obs_x_CR_LowMeff_ttbar_1l2tau","nbins":1}],"contents":[236],"name":"obsData_CR_LowMeff_ttbar_1l2tau","type":"binned"},{"axes":[{"max":4.0,"min":0.0,"name":"obs_x_CR_VV_3l0tau_2or3j_HT_lep","nbins":4}],"contents":[320,536,160,114],"name":"obsData_CR_VV_3l0tau_2or3j_HT_lep","type":"binned"},{"axes":[{"max":3.0,"min":0.0,"name":"obs_x_CR_ttW_2lSS0tau_neg_HT_lep","nbins":3}],"contents":[407,191,92],"name":"obsData_CR_ttW_2lSS0tau_neg_HT_lep","type":"binned"},{"axes":[{"max":3.0,"min":0.0,"name":"obs_x_CR_ttW_2lSS0tau_pos_HT_lep","nbins":3}],"contents":[577,285,120],"name":"obsData_CR_ttW_2lSS0tau_pos_HT_lep","type":"binned"},{"axes":[{"max":4.0,"min":0.0,"name":"obs_x_CR_ttZ_3l0tau_njets4_HT_lep","nbins":4}],"contents":[99,298,133,102],"name":"obsData_CR_ttZ_3l0tau_njets4_HT_lep","type":"binned"},{"axes":[{"max":5.0,"min":0.0,"name":"obs_x_SR_1l1tau_OS","nbins":5}],"contents":[206,97,30,5,1],"name":"obsData_SR_1l1tau_OS","type":"binned"},{"axes":[{"max":4.0,"min":0.0,"name":"obs_x_SR_1l1tau_SS","nbins":4}],"contents":[12,4,2,1],"name":"obsData_SR_1l1tau_SS","type":"binned"},{"axes":[{"max":4.0,"min":0.0,"name":"obs_x_SR_1l2tau","nbins":4}],"contents":[6,0,0,0],"name":"obsData_SR_1l2tau","type":"binned"},{"axes":[{"max":5.0,"min":0.0,"name":"obs_x_SR_2lOS1tau_Meff","nbins":5}],"contents":[6,4,3,0,0],"name":"obsData_SR_2lOS1tau_Meff","type":"binned"},{"axes":[{"max":3.0,"min":0.0,"name":"obs_x_SR_2lOS2tau_Meff","nbins":3}],"contents":[0,1,0],"name":"obsData_SR_2lOS2tau_Meff","type":"binned"},{"axes":[{"max":3.0,"min":0.0,"name":"obs_x_SR_2lSSor3l1tau_tauPt125_Meff","nbins":3}],"contents":[5,2,0],"name":"obsData_SR_2lSSor3l1tau_tauPt125_Meff","type":"binned"},{"axes":[{"max":3.0,"min":0.0,"name":"obs_x_SR_2lSSor3l1tau_tauPt225_Meff","nbins":3}],"contents":[1,2,0],"name":"obsData_SR_2lSSor3l1tau_tauPt225_Meff","type":"binned"}],"distributions":[{"axes":[{"max":1.0,"min":0.0,"name":"obs_x_CR_ExtCo_2lSS0tau_Nevt","nbins":1}],"name":"model_CR_ExtCo_2lSS0tau_Nevt","samples":[{"data":{"contents":[0.8014254936608665]},"modifiers":[{"constraint_name":"lumiConstraint","name":"Lumi","parameter":"Lumi","type":"normfactor"},{"name":"SigXsecOverSM","parameter":"SigXsecOverSM","type":"normfactor"},{"constraint":"Gauss","data":{"hi":1.021,"lo":0.979227},"name":"ATLAS_EL_SF_ID","parameter":"alpha_ATLAS_EL_SF_ID","type":"normsys"},{"constraint":"Gauss","data":{"hi":1.01597,"lo":0.984035},"name":"ATLAS_MU_SF_Isol_Stat","parameter":"alpha_ATLAS_MU_SF_Isol_Stat","type":"normsys"},{"constraint":"Gauss","data":{"hi":1.01667,"lo":0.983332},"name":"ATLAS_MU_SF_Isol_Syst","parameter":"alpha_ATLAS_MU_SF_Isol_Syst","type":"normsys"},{"constraint":"Gauss","data":{"hi":1.07755,"lo":0.922454},"name":"ATLAS_PRW_DATASF","parameter":"alpha_ATLAS_PRW_DATASF","type":"normsys"},{"constraint":"Gauss","data":{"hi":1.02,"lo":0.98},"name":"ATLAS_lumi","parameter":"alpha_ATLAS_lumi","type":"normsys"},{"constraint":"Gauss","data":{"hi":1.01,"lo":0.99},"name":"LQSignal_Acceptance_PDF_lowmass","parameter":"alpha_LQSignal_Acceptance_PDF_lowmass","type":"normsys"},{"constraint":"Gauss","data":{"hi":1.05,"lo":0.95},"name":"LQSignal_Acceptance_Var3c","parameter":"alpha_LQSignal_Acceptance_Var3c","type":"normsys"},{"constraint":"Gauss","data":{"hi":1.05,"lo":0.95},"name":"LQSignal_Acceptance_scale","parameter":"alpha_LQSignal_Acceptance_scale","type":"normsys"}],"name":"LQd_M600_B0p7"}],"type":"histfactory_dist"},{"mean":"nominalLumi","name":"lumiConstraint","sigma":0.10000000149011612,"type":"gaussian_dist","x":"Lumi"},{"axes":[{"max":1.0,"min":0.0,"name":"obs_x_CR_ExtCo_3l0tau_Nevt","nbins":1}],"name":"model_CR_ExtCo_3l0tau_Nevt","samples":[{"data":{"contents":[0.3700724268729991]},"modifiers":[{"constraint_name":"lumiConstraint","name":"Lumi","parameter":"Lumi","type":"normfactor"},{"name":"SigXsecOverSM","parameter":"SigXsecOverSM","type":"normfactor"},{"constraint":"Gauss","data":{"hi":1.03184,"lo":0.968556},"name":"ATLAS_EL_SF_ID","parameter":"alpha_ATLAS_EL_SF_ID","type":"normsys"},{"constraint":"Gauss","data":{"hi":1.02569,"lo":0.974308},"name":"ATLAS_FTAG_EXTRAP_C","parameter":"alpha_ATLAS_FTAG_EXTRAP_C","type":"normsys"},{"constraint":"Gauss","data":{"hi":1.33144,"lo":0.668564},"name":"ATLAS_JES_NP_Stat3","parameter":"alpha_ATLAS_JES_NP_Stat3","type":"normsys"},{"constraint":"Gauss","data":{"hi":1.33142,"lo":0.668581},"name":"ATLAS_JES_NP_Stat4","parameter":"alpha_ATLAS_JES_NP_Stat4","type":"normsys"},{"constraint":"Gauss","data":{"hi":0.950073,"lo":1.04993},"name":"ATLAS_PRW_DATASF","parameter":"alpha_ATLAS_PRW_DATASF","type":"normsys"},{"constraint":"Gauss","data":{"hi":1.02,"lo":0.98},"name":"ATLAS_lumi","parameter":"alpha_ATLAS_lumi","type":"normsys"},{"constraint":"Gauss","data":{"hi":1.05,"lo":0.95},"name":"LQSignal_Acceptance_Var3c","parameter":"alpha_LQSignal_Acceptance_Var3c","type":"normsys"},{"constraint":"Gauss","data":{"hi":1.05,"lo":0.95},"name":"LQSignal_Acceptance_scale","parameter":"alpha_LQSignal_Acceptance_scale","type":"normsys"}],"name":"LQd_M600_B0p7"}],"type":"histfactory_dist"},{"axes":[{"max":3.0,"min":0.0,"name":"obs_x_CR_HFe_2lSS0tau_neg_HT_lep","nbins":3}],"name":"model_CR_HFe_2lSS0tau_neg_HT_lep","samples":[{"data":{"contents":[0.06068041282456738,0.32422890918500286,1.03060734924133]},"modifiers":[{"constraint_name":"lumiConstraint","name":"Lumi","parameter":"Lumi","type":"normfactor"},{"name":"SigXsecOverSM","parameter":"SigXsecOverSM","type":"normfactor"},{"constraint":"Gauss","data":{"hi":1.01795,"lo":0.982312},"name":"ATLAS_EL_SF_ID","parameter":"alpha_ATLAS_EL_SF_ID","type":"normsys"},{"constraint":"Gauss","data":{"hi":0.986374,"lo":1.01363},"name":"ATLAS_JES_BJES","parameter":"alpha_ATLAS_JES_BJES","type":"normsys"},{"constraint":"Gauss","data":{"hi":0.985842,"lo":1.01416},"name":"ATLAS_JES_EtaInter_Model","parameter":"alpha_ATLAS_JES_EtaInter_Model","type":"normsys"},{"constraint":"Gauss","data":{"hi":0.980831,"lo":1.01917},"name":"ATLAS_JES_EtaInter_Stat","parameter":"alpha_ATLAS_JES_EtaInter_Stat","type":"normsys"},{"constraint":"Gauss","data":{"hi":0.95953,"lo":1.04047},"name":"ATLAS_JES_Flavor_Comp","parameter":"alpha_ATLAS_JES_Flavor_Comp","type":"normsys"},{"constraint":"Gauss","data":{"hi":1.02519,"lo":0.974815},"name":"ATLAS_JES_Flavor_Resp","parameter":"alpha_ATLAS_JES_Flavor_Resp","type":"normsys"},{"constraint":"Gauss","data":{"hi":0.975471,"lo":1.02453},"name":"ATLAS_JES_NP_Mod1","parameter":"alpha_ATLAS_JES_NP_Mod1","type":"normsys"},{"constraint":"Gauss","data":{"hi":1.01756,"lo":0.982444},"name":"ATLAS_JES_PU_OffsetMu","parameter":"alpha_ATLAS_JES_PU_OffsetMu","type":"normsys"},{"constraint":"Gauss","data":{"hi":0.946049,"lo":1.05395},"name":"ATLAS_JES_PU_Rho","parameter":"alpha_ATLAS_JES_PU_Rho","type":"normsys"},{"constraint":"Gauss","data":{"hi":1.01426,"lo":0.985738},"name":"ATLAS_MU_SF_Isol_Stat","parameter":"alpha_ATLAS_MU_SF_Isol_Stat","type":"normsys"},{"constraint":"Gauss","data":{"hi":1.01498,"lo":0.985021},"name":"ATLAS_MU_SF_Isol_Syst","parameter":"alpha_ATLAS_MU_SF_Isol_Syst","type":"normsys"},{"constraint":"Gauss","data":{"hi":1.01791,"lo":0.982093},"name":"ATLAS_PRW_DATASF","parameter":"alpha_ATLAS_PRW_DATASF","type":"normsys"},{"constraint":"Gauss","data":{"hi":1.02,"lo":0.98},"name":"ATLAS_lumi","parameter":"alpha_ATLAS_lumi","type":"normsys"},{"constraint":"Gauss","data":{"hi":1.05,"lo":0.95},"name":"LQSignal_Acceptance_Var3c","parameter":"alpha_LQSignal_Acceptance_Var3c","type":"normsys"},{"constraint":"Gauss","data":{"hi":1.05,"lo":0.95},"name":"LQSignal_Acceptance_scale","parameter":"alpha_LQSignal_Acceptance_scale","type":"normsys"}],"name":"LQd_M600_B0p7"}],"type":"histfactory_dist"},{"axes":[{"max":3.0,"min":0.0,"name":"obs_x_CR_HFe_2lSS0tau_pos_HT_lep","nbins":3}],"name":"model_CR_HFe_2lSS0tau_pos_HT_lep","samples":[{"data":{"contents":[0.0953806820905769,0.25617609792371737,1.0765934294801478]},"modifiers":[{"constraint_name":"lumiConstraint","name":"Lumi","parameter":"Lumi","type":"normfactor"},{"name":"SigXsecOverSM","parameter":"SigXsecOverSM","type":"normfactor"},{"constraint":"Gauss","data":{"hi":0.986069,"lo":1.01393},"name":"ATLAS_EG_SCALE","parameter":"alpha_ATLAS_EG_SCALE","type":"normsys"},{"constraint":"Gauss","data":{"hi":1.01676,"lo":0.983434},"name":"ATLAS_EL_SF_ID","parameter":"alpha_ATLAS_EL_SF_ID","type":"normsys"},{"constraint":"Gauss","data":{"hi":0.977168,"lo":1.02283},"name":"ATLAS_JES_Flavor_Comp","parameter":"alpha_ATLAS_JES_Flavor_Comp","type":"normsys"},{"constraint":"Gauss","data":{"hi":1.01428,"lo":0.985719},"name":"ATLAS_JES_Flavor_Resp","parameter":"alpha_ATLAS_JES_Flavor_Resp","type":"normsys"},{"constraint":"Gauss","data":{"hi":0.985803,"lo":1.0142},"name":"ATLAS_JES_NP_Mod1","parameter":"alpha_ATLAS_JES_NP_Mod1","type":"normsys"},{"constraint":"Gauss","data":{"hi":0.987565,"lo":1.01244},"name":"ATLAS_MU_MS","parameter":"alpha_ATLAS_MU_MS","type":"normsys"},{"constraint":"Gauss","data":{"hi":1.01436,"lo":0.985644},"name":"ATLAS_MU_SF_Isol_Stat","parameter":"alpha_ATLAS_MU_SF_Isol_Stat","type":"normsys"},{"constraint":"Gauss","data":{"hi":1.01525,"lo":0.984749},"name":"ATLAS_MU_SF_Isol_Syst","parameter":"alpha_ATLAS_MU_SF_Isol_Syst","type":"normsys"},{"constraint":"Gauss","data":{"hi":0.989609,"lo":1.01039},"name":"ATLAS_PRW_DATASF","parameter":"alpha_ATLAS_PRW_DATASF","type":"normsys"},{"constraint":"Gauss","data":{"hi":1.02,"lo":0.98},"name":"ATLAS_lumi","parameter":"alpha_ATLAS_lumi","type":"normsys"},{"constraint":"Gauss","data":{"hi":1.01,"lo":0.99},"name":"LQSignal_Acceptance_PDF_lowmass","parameter":"alpha_LQSignal_Acceptance_PDF_lowmass","type":"normsys"},{"constraint":"Gauss","data":{"hi":1.05,"lo":0.95},"name":"LQSignal_Acceptance_Var3c","parameter":"alpha_LQSignal_Acceptance_Var3c","type":"normsys"},{"constraint":"Gauss","data":{"hi":1.05,"lo":0.95},"name":"LQSignal_Acceptance_scale","parameter":"alpha_LQSignal_Acceptance_scale","type":"normsys"}],"name":"LQd_M600_B0p7"}],"type":"histfactory_dist"},{"axes":[{"max":3.0,"min":0.0,"name":"obs_x_CR_HFmu_2lSS0tau_neg_HT_lep","nbins":3}],"name":"model_CR_HFmu_2lSS0tau_neg_HT_lep","samples":[{"data":{"contents":[0.08593755170204107,0.37610712312692274,0.9291723323407197]},"modifiers":[{"constraint_name":"lumiConstraint","name":"Lumi","parameter":"Lumi","type":"normfactor"},{"name":"SigXsecOverSM","parameter":"SigXsecOverSM","type":"normfactor"},{"constraint":"Gauss","data":{"hi":1.01255,"lo":0.987449},"name":"ATLAS_EL_SF_ID","parameter":"alpha_ATLAS_EL_SF_ID","type":"normsys"},{"constraint":"Gauss","data":{"hi":0.941408,"lo":1.05859},"name":"ATLAS_JES_Flavor_Comp","parameter":"alpha_ATLAS_JES_Flavor_Comp","type":"normsys"},{"constraint":"Gauss","data":{"hi":1.03291,"lo":0.967085},"name":"ATLAS_JES_Flavor_Resp","parameter":"alpha_ATLAS_JES_Flavor_Resp","type":"normsys"},{"constraint":"Gauss","data":{"hi":0.986466,"lo":1.01353},"name":"ATLAS_JES_NP_Mod1","parameter":"alpha_ATLAS_JES_NP_Mod1","type":"normsys"},{"constraint":"Gauss","data":{"hi":0.942859,"lo":1.05714},"name":"ATLAS_JES_PU_Rho","parameter":"alpha_ATLAS_JES_PU_Rho","type":"normsys"},{"constraint":"Gauss","data":{"hi":0.977388,"lo":1.01817},"name":"ATLAS_JVT","parameter":"alpha_ATLAS_JVT","type":"normsys"},{"constraint":"Gauss","data":{"hi":1.02,"lo":0.98},"name":"ATLAS_lumi","parameter":"alpha_ATLAS_lumi","type":"normsys"},{"constraint":"Gauss","data":{"hi":1.01,"lo":0.99},"name":"LQSignal_Acceptance_PDF_lowmass","parameter":"alpha_LQSignal_Acceptance_PDF_lowmass","type":"normsys"},{"constraint":"Gauss","data":{"hi":1.05,"lo":0.95},"name":"LQSignal_Acceptance_Var3c","parameter":"alpha_LQSignal_Acceptance_Var3c","type":"normsys"},{"constraint":"Gauss","data":{"hi":1.05,"lo":0.95},"name":"LQSignal_Acceptance_scale","parameter":"alpha_LQSignal_Acceptance_scale","type":"normsys"}],"name":"LQd_M600_B0p7"}],"type":"histfactory_dist"},{"axes":[{"max":3.0,"min":0.0,"name":"obs_x_CR_HFmu_2lSS0tau_pos_HT_lep","nbins":3}],"name":"model_CR_HFmu_2lSS0tau_pos_HT_lep","samples":[{"data":{"contents":[0.19993531116325336,0.4127858838721352,0.9330960682934917]},"modifiers":[{"constraint_name":"lumiConstraint","name":"Lumi","parameter":"Lumi","type":"normfactor"},{"name":"SigXsecOverSM","parameter":"SigXsecOverSM","type":"normfactor"},{"constraint":"Gauss","data":{"hi":1.02515,"lo":0.974848},"name":"ATLAS_FTAG_EXTRAP_C","parameter":"alpha_ATLAS_FTAG_EXTRAP_C","type":"normsys"},{"constraint":"Gauss","data":{"hi":0.977259,"lo":1.02274},"name":"ATLAS_JES_Flavor_Comp","parameter":"alpha_ATLAS_JES_Flavor_Comp","type":"normsys"},{"constraint":"Gauss","data":{"hi":1.01264,"lo":0.987359},"name":"ATLAS_JES_Flavor_Resp","parameter":"alpha_ATLAS_JES_Flavor_Resp","type":"normsys"},{"constraint":"Gauss","data":{"hi":0.975397,"lo":1.0246},"name":"ATLAS_JES_PU_Rho","parameter":"alpha_ATLAS_JES_PU_Rho","type":"normsys"},{"constraint":"Gauss","data":{"hi":1.01808,"lo":0.981919},"name":"ATLAS_PRW_DATASF","parameter":"alpha_ATLAS_PRW_DATASF","type":"normsys"},{"constraint":"Gauss","data":{"hi":1.02,"lo":0.98},"name":"ATLAS_lumi","parameter":"alpha_ATLAS_lumi","type":"normsys"},{"constraint":"Gauss","data":{"hi":1.05,"lo":0.95},"name":"LQSignal_Acceptance_Var3c","parameter":"alpha_LQSignal_Acceptance_Var3c","type":"normsys"},{"constraint":"Gauss","data":{"hi":1.05,"lo":0.95},"name":"LQSignal_Acceptance_scale","parameter":"alpha_LQSignal_Acceptance_scale","type":"normsys"}],"name":"LQd_M600_B0p7"}],"type":"histfactory_dist"},{"axes":[{"max":1.0,"min":0.0,"name":"obs_x_CR_IntCo_2lSS0tau_Nevt","nbins":1}],"name":"model_CR_IntCo_2lSS0tau_Nevt","samples":[{"data":{"contents":[0.05300592209147224]},"modifiers":[{"constraint_name":"lumiConstraint","name":"Lumi","parameter":"Lumi","type":"normfactor"},{"name":"SigXsecOverSM","parameter":"SigXsecOverSM","type":"normfactor"},{"constraint":"Gauss","data":{"hi":1.02203,"lo":0.977934},"name":"ATLAS_EL_SF_ID","parameter":"alpha_ATLAS_EL_SF_ID","type":"normsys"},{"constraint":"Gauss","data":{"hi":0.978042,"lo":1.02196},"name":"ATLAS_FTAG_B0","parameter":"alpha_ATLAS_FTAG_B0","type":"normsys"},{"constraint":"Gauss","data":{"hi":1.01683,"lo":0.983165},"name":"ATLAS_FTAG_B1","parameter":"alpha_ATLAS_FTAG_B1","type":"normsys"},{"constraint":"Gauss","data":{"hi":1.01756,"lo":0.982443},"name":"ATLAS_FTAG_B3","parameter":"alpha_ATLAS_FTAG_B3","type":"normsys"},{"constraint":"Gauss","data":{"hi":1.04882,"lo":0.951185},"name":"ATLAS_FTAG_C0","parameter":"alpha_ATLAS_FTAG_C0","type":"normsys"},{"constraint":"Gauss","data":{"hi":1.02144,"lo":0.978562},"name":"ATLAS_FTAG_C1","parameter":"alpha_ATLAS_FTAG_C1","type":"normsys"},{"constraint":"Gauss","data":{"hi":0.924374,"lo":1.07563},"name":"ATLAS_FTAG_EXTRAP_C","parameter":"alpha_ATLAS_FTAG_EXTRAP_C","type":"normsys"},{"constraint":"Gauss","data":{"hi":0.746352,"lo":1.25365},"name":"ATLAS_JES_NP_Mod1","parameter":"alpha_ATLAS_JES_NP_Mod1","type":"normsys"},{"constraint":"Gauss","data":{"hi":1.06896,"lo":0.931037},"name":"ATLAS_JES_NP_Mod4","parameter":"alpha_ATLAS_JES_NP_Mod4","type":"normsys"},{"constraint":"Gauss","data":{"hi":0.931034,"lo":1.06897},"name":"ATLAS_JES_NP_Stat1","parameter":"alpha_ATLAS_JES_NP_Stat1","type":"normsys"},{"constraint":"Gauss","data":{"hi":0.948137,"lo":1.04306},"name":"ATLAS_JVT","parameter":"alpha_ATLAS_JVT","type":"normsys"},{"constraint":"Gauss","data":{"hi":1.43398,"lo":0.566017},"name":"ATLAS_PRW_DATASF","parameter":"alpha_ATLAS_PRW_DATASF","type":"normsys"},{"constraint":"Gauss","data":{"hi":1.02,"lo":0.98},"name":"ATLAS_lumi","parameter":"alpha_ATLAS_lumi","type":"normsys"},{"constraint":"Gauss","data":{"hi":1.05,"lo":0.95},"name":"LQSignal_Acceptance_Var3c","parameter":"alpha_LQSignal_Acceptance_Var3c","type":"normsys"},{"constraint":"Gauss","data":{"hi":1.05,"lo":0.95},"name":"LQSignal_Acceptance_scale","parameter":"alpha_LQSignal_Acceptance_scale","type":"normsys"}],"name":"LQd_M600_B0p7"}],"type":"histfactory_dist"},{"axes":[{"max":1.0,"min":0.0,"name":"obs_x_CR_IntCo_3l0tau_Nevt","nbins":1}],"name":"model_CR_IntCo_3l0tau_Nevt","samples":[{"data":{"contents":[1e-06]},"modifiers":[{"constraint_name":"lumiConstraint","name":"Lumi","parameter":"Lumi","type":"normfactor"},{"name":"SigXsecOverSM","parameter":"SigXsecOverSM","type":"normfactor"},{"constraint":"Gauss","data":{"hi":0.0,"lo":2.0},"name":"ATLAS_PRW_DATASF","parameter":"alpha_ATLAS_PRW_DATASF","type":"normsys"},{"constraint":"Gauss","data":{"hi":1.02,"lo":0.98},"name":"ATLAS_lumi","parameter":"alpha_ATLAS_lumi","type":"normsys"}],"name":"LQd_M600_B0p7"}],"type":"histfactory_dist"},{"axes":[{"max":1.0,"min":0.0,"name":"obs_x_CR_LowMeff_ttbar_1l1tau_OS","nbins":1}],"name":"model_CR_LowMeff_ttbar_1l1tau_OS","samples":[{"data":{"contents":[7.111285581068697]},"modifiers":[{"constraint_name":"lumiConstraint","name":"Lumi","parameter":"Lumi","type":"normfactor"},{"name":"SigXsecOverSM","parameter":"SigXsecOverSM","type":"normfactor"},{"constraint":"Gauss","data":{"hi":1.02382,"lo":0.97618},"name":"ATLAS_FTAG_B0","parameter":"alpha_ATLAS_FTAG_B0","type":"normsys"},{"constraint":"Gauss","data":{"hi":1.01595,"lo":0.984053},"name":"ATLAS_FTAG_EXTRAP_C","parameter":"alpha_ATLAS_FTAG_EXTRAP_C","type":"normsys"},{"constraint":"Gauss","data":{"hi":0.938891,"lo":1.06111},"name":"ATLAS_JES_EtaInter_Model","parameter":"alpha_ATLAS_JES_EtaInter_Model","type":"normsys"},{"constraint":"Gauss","data":{"hi":0.931145,"lo":1.06886},"name":"ATLAS_JES_Flavor_Comp","parameter":"alpha_ATLAS_JES_Flavor_Comp","type":"normsys"},{"constraint":"Gauss","data":{"hi":1.07466,"lo":0.925339},"name":"ATLAS_JES_Flavor_Resp","parameter":"alpha_ATLAS_JES_Flavor_Resp","type":"normsys"},{"constraint":"Gauss","data":{"hi":0.989652,"lo":1.01035},"name":"ATLAS_JES_NP_Mix1","parameter":"alpha_ATLAS_JES_NP_Mix1","type":"normsys"},{"constraint":"Gauss","data":{"hi":1.01049,"lo":0.989511},"name":"ATLAS_JES_NP_Mix2","parameter":"alpha_ATLAS_JES_NP_Mix2","type":"normsys"},{"constraint":"Gauss","data":{"hi":0.987705,"lo":1.0123},"name":"ATLAS_JES_NP_Mod1","parameter":"alpha_ATLAS_JES_NP_Mod1","type":"normsys"},{"constraint":"Gauss","data":{"hi":0.989813,"lo":1.01019},"name":"ATLAS_JES_NP_Mod2","parameter":"alpha_ATLAS_JES_NP_Mod2","type":"normsys"},{"constraint":"Gauss","data":{"hi":1.01456,"lo":0.985439},"name":"ATLAS_JES_NP_Mod3","parameter":"alpha_ATLAS_JES_NP_Mod3","type":"normsys"},{"constraint":"Gauss","data":{"hi":1.01035,"lo":0.989647},"name":"ATLAS_JES_NP_Stat3","parameter":"alpha_ATLAS_JES_NP_Stat3","type":"normsys"},{"constraint":"Gauss","data":{"hi":0.976671,"lo":1.02333},"name":"ATLAS_JES_PU_OffsetMu","parameter":"alpha_ATLAS_JES_PU_OffsetMu","type":"normsys"},{"constraint":"Gauss","data":{"hi":0.951081,"lo":1.04892},"name":"ATLAS_JES_PU_OffsetNPV","parameter":"alpha_ATLAS_JES_PU_OffsetNPV","type":"normsys"},{"constraint":"Gauss","data":{"hi":0.95098,"lo":1.04902},"name":"ATLAS_JES_PU_Rho","parameter":"alpha_ATLAS_JES_PU_Rho","type":"normsys"},{"constraint":"Gauss","data":{"hi":1.01366,"lo":0.98634},"name":"ATLAS_MET_Perp","parameter":"alpha_ATLAS_MET_Perp","type":"normsys"},{"constraint":"Gauss","data":{"hi":0.987392,"lo":1.01261},"name":"ATLAS_MET_Scale","parameter":"alpha_ATLAS_MET_Scale","type":"normsys"},{"constraint":"Gauss","data":{"hi":1.02532,"lo":0.988171},"name":"ATLAS_TAU_SF_ELEOLR","parameter":"alpha_ATLAS_TAU_SF_ELEOLR","type":"normsys"},{"constraint":"Gauss","data":{"hi":1.01612,"lo":0.997375},"name":"ATLAS_TAU_SF_RECO","parameter":"alpha_ATLAS_TAU_SF_RECO","type":"normsys"},{"constraint":"Gauss","data":{"hi":1.05708,"lo":0.956409},"name":"ATLAS_TAU_SF_RECO_AFII","parameter":"alpha_ATLAS_TAU_SF_RECO_AFII","type":"normsys"},{"constraint":"Gauss","data":{"hi":1.01431,"lo":0.999186},"name":"ATLAS_TAU_SF_RNNID_1PGE40","parameter":"alpha_ATLAS_TAU_SF_RNNID_1PGE40","type":"normsys"},{"constraint":"Gauss","data":{"hi":1.02449,"lo":0.989005},"name":"ATLAS_TAU_SF_RNNID_SYST","parameter":"alpha_ATLAS_TAU_SF_RNNID_SYST","type":"normsys"},{"constraint":"Gauss","data":{"hi":0.92956,"lo":1.07044},"name":"ATLAS_TAU_TES_DET_LOWPT_TAU","parameter":"alpha_ATLAS_TAU_TES_DET_LOWPT_TAU","type":"normsys"},{"constraint":"Gauss","data":{"hi":1.0159,"lo":0.984097},"name":"ATLAS_TRUETAU_RW_STAT","parameter":"alpha_ATLAS_TRUETAU_RW_STAT","type":"normsys"},{"constraint":"Gauss","data":{"hi":1.02,"lo":0.98},"name":"ATLAS_lumi","parameter":"alpha_ATLAS_lumi","type":"normsys"},{"constraint":"Gauss","data":{"hi":1.01,"lo":0.99},"name":"LQSignal_Acceptance_PDF_lowmass","parameter":"alpha_LQSignal_Acceptance_PDF_lowmass","type":"normsys"},{"constraint":"Gauss","data":{"hi":1.081,"lo":0.919},"name":"LQSignal_Acceptance_Var3c","parameter":"alpha_LQSignal_Acceptance_Var3c","type":"normsys"},{"constraint":"Gauss","data":{"hi":1.027,"lo":0.973},"name":"LQSignal_Acceptance_scale","parameter":"alpha_LQSignal_Acceptance_scale","type":"normsys"}],"name":"LQd_M600_B0p7"}],"type":"histfactory_dist"},{"axes":[{"max":1.0,"min":0.0,"name":"obs_x_CR_LowMeff_ttbar_1l1tau_SS","nbins":1}],"name":"model_CR_LowMeff_ttbar_1l1tau_SS","samples":[{"data":{"contents":[4.1714338776069955]},"modifiers":[{"constraint_name":"lumiConstraint","name":"Lumi","parameter":"Lumi","type":"normfactor"},{"name":"SigXsecOverSM","parameter":"SigXsecOverSM","type":"normfactor"},{"constraint":"Gauss","data":{"hi":1.01513,"lo":0.984872},"name":"ATLAS_FTAG_B0","parameter":"alpha_ATLAS_FTAG_B0","type":"normsys"},{"constraint":"Gauss","data":{"hi":1.01289,"lo":0.987115},"name":"ATLAS_FTAG_EXTRAP_C","parameter":"alpha_ATLAS_FTAG_EXTRAP_C","type":"normsys"},{"constraint":"Gauss","data":{"hi":0.978922,"lo":1.02108},"name":"ATLAS_JES_EtaInter_Model","parameter":"alpha_ATLAS_JES_EtaInter_Model","type":"normsys"},{"constraint":"Gauss","data":{"hi":0.97387,"lo":1.02613},"name":"ATLAS_JES_Flavor_Comp","parameter":"alpha_ATLAS_JES_Flavor_Comp","type":"normsys"},{"constraint":"Gauss","data":{"hi":1.04095,"lo":0.959051},"name":"ATLAS_JES_Flavor_Resp","parameter":"alpha_ATLAS_JES_Flavor_Resp","type":"normsys"},{"constraint":"Gauss","data":{"hi":0.965675,"lo":1.03433},"name":"ATLAS_JES_NP_Mod1","parameter":"alpha_ATLAS_JES_NP_Mod1","type":"normsys"},{"constraint":"Gauss","data":{"hi":0.984758,"lo":1.01524},"name":"ATLAS_JES_PU_OffsetNPV","parameter":"alpha_ATLAS_JES_PU_OffsetNPV","type":"normsys"},{"constraint":"Gauss","data":{"hi":0.969142,"lo":1.03086},"name":"ATLAS_JES_PU_Rho","parameter":"alpha_ATLAS_JES_PU_Rho","type":"normsys"},{"constraint":"Gauss","data":{"hi":1.02606,"lo":0.987855},"name":"ATLAS_TAU_SF_ELEOLR","parameter":"alpha_ATLAS_TAU_SF_ELEOLR","type":"normsys"},{"constraint":"Gauss","data":{"hi":1.0156,"lo":0.998315},"name":"ATLAS_TAU_SF_RECO","parameter":"alpha_ATLAS_TAU_SF_RECO","type":"normsys"},{"constraint":"Gauss","data":{"hi":1.05717,"lo":0.95675},"name":"ATLAS_TAU_SF_RECO_AFII","parameter":"alpha_ATLAS_TAU_SF_RECO_AFII","type":"normsys"},{"constraint":"Gauss","data":{"hi":1.01497,"lo":0.998948},"name":"ATLAS_TAU_SF_RNNID_1PGE40","parameter":"alpha_ATLAS_TAU_SF_RNNID_1PGE40","type":"normsys"},{"constraint":"Gauss","data":{"hi":1.02442,"lo":0.989492},"name":"ATLAS_TAU_SF_RNNID_SYST","parameter":"alpha_ATLAS_TAU_SF_RNNID_SYST","type":"normsys"},{"constraint":"Gauss","data":{"hi":0.981568,"lo":1.01843},"name":"ATLAS_TAU_TES_DET_HIGHPT_TAU_1p","parameter":"alpha_ATLAS_TAU_TES_DET_HIGHPT_TAU_1p","type":"normsys"},{"constraint":"Gauss","data":{"hi":0.971813,"lo":1.02819},"name":"ATLAS_TAU_TES_DET_LOWPT_TAU","parameter":"alpha_ATLAS_TAU_TES_DET_LOWPT_TAU","type":"normsys"},{"constraint":"Gauss","data":{"hi":1.01489,"lo":0.985113},"name":"ATLAS_TRUETAU_RW_STAT","parameter":"alpha_ATLAS_TRUETAU_RW_STAT","type":"normsys"},{"constraint":"Gauss","data":{"hi":1.02,"lo":0.98},"name":"ATLAS_lumi","parameter":"alpha_ATLAS_lumi","type":"normsys"},{"constraint":"Gauss","data":{"hi":1.016,"lo":0.984},"name":"LQSignal_Acceptance_PDF_lowmass","parameter":"alpha_LQSignal_Acceptance_PDF_lowmass","type":"normsys"},{"constraint":"Gauss","data":{"hi":1.047,"lo":0.953},"name":"LQSignal_Acceptance_Var3c","parameter":"alpha_LQSignal_Acceptance_Var3c","type":"normsys"},{"constraint":"Gauss","data":{"hi":1.052,"lo":0.948},"name":"LQSignal_Acceptance_scale","parameter":"alpha_LQSignal_Acceptance_scale","type":"normsys"}],"name":"LQd_M600_B0p7"}],"type":"histfactory_dist"},{"axes":[{"max":1.0,"min":0.0,"name":"obs_x_CR_LowMeff_ttbar_1l2tau","nbins":1}],"name":"model_CR_LowMeff_ttbar_1l2tau","samples":[{"data":{"contents":[3.5491358479697457]},"modifiers":[{"constraint_name":"lumiConstraint","name":"Lumi","parameter":"Lumi","type":"normfactor"},{"name":"SigXsecOverSM","parameter":"SigXsecOverSM","type":"normfactor"},{"constraint":"Gauss","data":{"hi":1.02069,"lo":0.979309},"name":"ATLAS_FTAG_B0","parameter":"alpha_ATLAS_FTAG_B0","type":"normsys"},{"constraint":"Gauss","data":{"hi":1.22694,"lo":0.773061},"name":"ATLAS_JES_EtaInter_NonClosurePosEta","parameter":"alpha_ATLAS_JES_EtaInter_NonClosurePosEta","type":"normsys"},{"constraint":"Gauss","data":{"hi":0.749144,"lo":1.25086},"name":"ATLAS_JES_Flavor_Comp","parameter":"alpha_ATLAS_JES_Flavor_Comp","type":"normsys"},{"constraint":"Gauss","data":{"hi":1.25225,"lo":0.747746},"name":"ATLAS_JES_Flavor_Resp","parameter":"alpha_ATLAS_JES_Flavor_Resp","type":"normsys"},{"constraint":"Gauss","data":{"hi":1.22437,"lo":0.775628},"name":"ATLAS_JES_NP_Det1","parameter":"alpha_ATLAS_JES_NP_Det1","type":"normsys"},{"constraint":"Gauss","data":{"hi":0.768461,"lo":1.23154},"name":"ATLAS_JES_NP_Mix1","parameter":"alpha_ATLAS_JES_NP_Mix1","type":"normsys"},{"constraint":"Gauss","data":{"hi":1.01301,"lo":0.986992},"name":"ATLAS_JES_NP_Mix2","parameter":"alpha_ATLAS_JES_NP_Mix2","type":"normsys"},{"constraint":"Gauss","data":{"hi":0.983218,"lo":1.01678},"name":"ATLAS_JES_NP_Mod1","parameter":"alpha_ATLAS_JES_NP_Mod1","type":"normsys"},{"constraint":"Gauss","data":{"hi":0.777218,"lo":1.22278},"name":"ATLAS_JES_NP_Mod3","parameter":"alpha_ATLAS_JES_NP_Mod3","type":"normsys"},{"constraint":"Gauss","data":{"hi":0.761629,"lo":1.23837},"name":"ATLAS_JES_PU_OffsetNPV","parameter":"alpha_ATLAS_JES_PU_OffsetNPV","type":"normsys"},{"constraint":"Gauss","data":{"hi":1.21449,"lo":0.785506},"name":"ATLAS_JES_PU_PtTerm","parameter":"alpha_ATLAS_JES_PU_PtTerm","type":"normsys"},{"constraint":"Gauss","data":{"hi":0.756257,"lo":1.24374},"name":"ATLAS_JES_PU_Rho","parameter":"alpha_ATLAS_JES_PU_Rho","type":"normsys"},{"constraint":"Gauss","data":{"hi":0.988908,"lo":1.01109},"name":"ATLAS_MET_Scale","parameter":"alpha_ATLAS_MET_Scale","type":"normsys"},{"constraint":"Gauss","data":{"hi":0.985475,"lo":1.01453},"name":"ATLAS_PRW_DATASF","parameter":"alpha_ATLAS_PRW_DATASF","type":"normsys"},{"constraint":"Gauss","data":{"hi":1.04788,"lo":0.978978},"name":"ATLAS_TAU_SF_ELEOLR","parameter":"alpha_ATLAS_TAU_SF_ELEOLR","type":"normsys"},{"constraint":"Gauss","data":{"hi":1.0317,"lo":0.994675},"name":"ATLAS_TAU_SF_RECO","parameter":"alpha_ATLAS_TAU_SF_RECO","type":"normsys"},{"constraint":"Gauss","data":{"hi":1.12096,"lo":0.911199},"name":"ATLAS_TAU_SF_RECO_AFII","parameter":"alpha_ATLAS_TAU_SF_RECO_AFII","type":"normsys"},{"constraint":"Gauss","data":{"hi":1.0131,"lo":1.0131},"name":"ATLAS_TAU_SF_RNNID_1P2530","parameter":"alpha_ATLAS_TAU_SF_RNNID_1P2530","type":"normsys"},{"constraint":"Gauss","data":{"hi":1.01369,"lo":1.01251},"name":"ATLAS_TAU_SF_RNNID_1P3040","parameter":"alpha_ATLAS_TAU_SF_RNNID_1P3040","type":"normsys"},{"constraint":"Gauss","data":{"hi":1.02876,"lo":0.997564},"name":"ATLAS_TAU_SF_RNNID_1PGE40","parameter":"alpha_ATLAS_TAU_SF_RNNID_1PGE40","type":"normsys"},{"constraint":"Gauss","data":{"hi":1.0131,"lo":1.01309},"name":"ATLAS_TAU_SF_RNNID_3P2530","parameter":"alpha_ATLAS_TAU_SF_RNNID_3P2530","type":"normsys"},{"constraint":"Gauss","data":{"hi":1.01314,"lo":1.01306},"name":"ATLAS_TAU_SF_RNNID_3P3040","parameter":"alpha_ATLAS_TAU_SF_RNNID_3P3040","type":"normsys"},{"constraint":"Gauss","data":{"hi":1.0171,"lo":1.0091},"name":"ATLAS_TAU_SF_RNNID_3PGE40","parameter":"alpha_ATLAS_TAU_SF_RNNID_3PGE40","type":"normsys"},{"constraint":"Gauss","data":{"hi":1.04766,"lo":0.979158},"name":"ATLAS_TAU_SF_RNNID_SYST","parameter":"alpha_ATLAS_TAU_SF_RNNID_SYST","type":"normsys"},{"constraint":"Gauss","data":{"hi":1.0131,"lo":1.0131},"name":"ATLAS_TAU_SF_TRUEELECTRON_ELEOLR_STAT","parameter":"alpha_ATLAS_TAU_SF_TRUEELECTRON_ELEOLR_STAT","type":"normsys"},{"constraint":"Gauss","data":{"hi":1.0131,"lo":1.0131},"name":"ATLAS_TAU_SF_TRUEELECTRON_ELEOLR_SYST","parameter":"alpha_ATLAS_TAU_SF_TRUEELECTRON_ELEOLR_SYST","type":"normsys"},{"constraint":"Gauss","data":{"hi":0.979121,"lo":1.02088},"name":"ATLAS_TAU_TES_DET_HIGHPT_TAU_1p","parameter":"alpha_ATLAS_TAU_TES_DET_HIGHPT_TAU_1p","type":"normsys"},{"constraint":"Gauss","data":{"hi":0.962729,"lo":1.03727},"name":"ATLAS_TAU_TES_DET_LOWPT_TAU","parameter":"alpha_ATLAS_TAU_TES_DET_LOWPT_TAU","type":"normsys"},{"constraint":"Gauss","data":{"hi":1.01916,"lo":0.981005},"name":"ATLAS_TRUETAU_RW_STAT","parameter":"alpha_ATLAS_TRUETAU_RW_STAT","type":"normsys"},{"constraint":"Gauss","data":{"hi":1.02,"lo":0.98},"name":"ATLAS_lumi","parameter":"alpha_ATLAS_lumi","type":"normsys"},{"constraint":"Gauss","data":{"hi":1.022,"lo":0.978},"name":"LQSignal_Acceptance_PDF_lowmass","parameter":"alpha_LQSignal_Acceptance_PDF_lowmass","type":"normsys"},{"constraint":"Gauss","data":{"hi":1.102,"lo":0.898},"name":"LQSignal_Acceptance_Var3c","parameter":"alpha_LQSignal_Acceptance_Var3c","type":"normsys"},{"constraint":"Gauss","data":{"hi":1.057,"lo":0.943},"name":"LQSignal_Acceptance_scale","parameter":"alpha_LQSignal_Acceptance_scale","type":"normsys"}],"name":"LQd_M600_B0p7"}],"type":"histfactory_dist"},{"axes":[{"max":4.0,"min":0.0,"name":"obs_x_CR_VV_3l0tau_2or3j_HT_lep","nbins":4}],"name":"model_CR_VV_3l0tau_2or3j_HT_lep","samples":[{"data":{"contents":[0.024755848256843353,0.2331368144372125,0.23243009874845566,0.11842979037201073]},"modifiers":[{"constraint_name":"lumiConstraint","name":"Lumi","parameter":"Lumi","type":"normfactor"},{"name":"SigXsecOverSM","parameter":"SigXsecOverSM","type":"normfactor"},{"constraint":"Gauss","data":{"hi":1.01047,"lo":0.989606},"name":"ATLAS_EL_SF_ID","parameter":"alpha_ATLAS_EL_SF_ID","type":"normsys"},{"constraint":"Gauss","data":{"hi":1.01144,"lo":0.988562},"name":"ATLAS_JES_BJES","parameter":"alpha_ATLAS_JES_BJES","type":"normsys"},{"constraint":"Gauss","data":{"hi":1.0115,"lo":0.988502},"name":"ATLAS_JES_EtaInter_Model","parameter":"alpha_ATLAS_JES_EtaInter_Model","type":"normsys"},{"constraint":"Gauss","data":{"hi":0.964087,"lo":1.03591},"name":"ATLAS_JES_Flavor_Comp","parameter":"alpha_ATLAS_JES_Flavor_Comp","type":"normsys"},{"constraint":"Gauss","data":{"hi":1.01887,"lo":0.981128},"name":"ATLAS_JES_Flavor_Resp","parameter":"alpha_ATLAS_JES_Flavor_Resp","type":"normsys"},{"constraint":"Gauss","data":{"hi":0.981015,"lo":1.01898},"name":"ATLAS_JES_PU_OffsetNPV","parameter":"alpha_ATLAS_JES_PU_OffsetNPV","type":"normsys"},{"constraint":"Gauss","data":{"hi":0.97493,"lo":1.02507},"name":"ATLAS_JES_PU_Rho","parameter":"alpha_ATLAS_JES_PU_Rho","type":"normsys"},{"constraint":"Gauss","data":{"hi":1.01734,"lo":0.982657},"name":"ATLAS_MU_MS","parameter":"alpha_ATLAS_MU_MS","type":"normsys"},{"constraint":"Gauss","data":{"hi":0.982378,"lo":1.01762},"name":"ATLAS_MU_SCALE","parameter":"alpha_ATLAS_MU_SCALE","type":"normsys"},{"constraint":"Gauss","data":{"hi":1.0449600000000001,"lo":0.955045},"name":"ATLAS_PRW_DATASF","parameter":"alpha_ATLAS_PRW_DATASF","type":"normsys"},{"constraint":"Gauss","data":{"hi":1.02,"lo":0.98},"name":"ATLAS_lumi","parameter":"alpha_ATLAS_lumi","type":"normsys"},{"constraint":"Gauss","data":{"hi":1.01,"lo":0.99},"name":"LQSignal_Acceptance_PDF_lowmass","parameter":"alpha_LQSignal_Acceptance_PDF_lowmass","type":"normsys"},{"constraint":"Gauss","data":{"hi":1.05,"lo":0.95},"name":"LQSignal_Acceptance_Var3c","parameter":"alpha_LQSignal_Acceptance_Var3c","type":"normsys"},{"constraint":"Gauss","data":{"hi":1.05,"lo":0.95},"name":"LQSignal_Acceptance_scale","parameter":"alpha_LQSignal_Acceptance_scale","type":"normsys"}],"name":"LQd_M600_B0p7"}],"type":"histfactory_dist"},{"axes":[{"max":3.0,"min":0.0,"name":"obs_x_CR_ttW_2lSS0tau_neg_HT_lep","nbins":3}],"name":"model_CR_ttW_2lSS0tau_neg_HT_lep","samples":[{"data":{"contents":[5.139513593267311,9.090735382801505,12.390566710208606]},"modifiers":[{"constraint_name":"lumiConstraint","name":"Lumi","parameter":"Lumi","type":"normfactor"},{"name":"SigXsecOverSM","parameter":"SigXsecOverSM","type":"normfactor"},{"constraint":"Gauss","data":{"hi":1.0105,"lo":0.989546},"name":"ATLAS_EL_SF_ID","parameter":"alpha_ATLAS_EL_SF_ID","type":"normsys"},{"constraint":"Gauss","data":{"hi":1.01142,"lo":0.988583},"name":"ATLAS_FTAG_EXTRAP_C","parameter":"alpha_ATLAS_FTAG_EXTRAP_C","type":"normsys"},{"constraint":"Gauss","data":{"hi":0.984884,"lo":1.01512},"name":"ATLAS_PRW_DATASF","parameter":"alpha_ATLAS_PRW_DATASF","type":"normsys"},{"constraint":"Gauss","data":{"hi":1.02,"lo":0.98},"name":"ATLAS_lumi","parameter":"alpha_ATLAS_lumi","type":"normsys"},{"constraint":"Gauss","data":{"hi":1.01,"lo":0.99},"name":"LQSignal_Acceptance_PDF_lowmass","parameter":"alpha_LQSignal_Acceptance_PDF_lowmass","type":"normsys"},{"constraint":"Gauss","data":{"hi":1.05,"lo":0.95},"name":"LQSignal_Acceptance_Var3c","parameter":"alpha_LQSignal_Acceptance_Var3c","type":"normsys"},{"constraint":"Gauss","data":{"hi":1.05,"lo":0.95},"name":"LQSignal_Acceptance_scale","parameter":"alpha_LQSignal_Acceptance_scale","type":"normsys"},{"constraint":"Gauss","data":{"hi":{"contents":[5.081062630411052,8.987347732092246,12.552405323774122]},"lo":{"contents":[5.196224248120228,9.191044788992903,12.23354664916429]}},"name":"ATLAS_PRW_DATASF","parameter":"alpha_ATLAS_PRW_DATASF","type":"histosys"}],"name":"LQd_M600_B0p7"}],"type":"histfactory_dist"},{"axes":[{"max":3.0,"min":0.0,"name":"obs_x_CR_ttW_2lSS0tau_pos_HT_lep","nbins":3}],"name":"model_CR_ttW_2lSS0tau_pos_HT_lep","samples":[{"data":{"contents":[4.454714316464828,10.074912169136176,11.067133650013945]},"modifiers":[{"constraint_name":"lumiConstraint","name":"Lumi","parameter":"Lumi","type":"normfactor"},{"name":"SigXsecOverSM","parameter":"SigXsecOverSM","type":"normfactor"},{"constraint":"Gauss","data":{"hi":1.01059,"lo":0.989477},"name":"ATLAS_EL_SF_ID","parameter":"alpha_ATLAS_EL_SF_ID","type":"normsys"},{"constraint":"Gauss","data":{"hi":1.01162,"lo":0.988376},"name":"ATLAS_FTAG_EXTRAP_C","parameter":"alpha_ATLAS_FTAG_EXTRAP_C","type":"normsys"},{"constraint":"Gauss","data":{"hi":1.01102,"lo":0.989},"name":"ATLAS_MU_SF_Isol_Syst","parameter":"alpha_ATLAS_MU_SF_Isol_Syst","type":"normsys"},{"constraint":"Gauss","data":{"hi":1.01043,"lo":0.989575},"name":"ATLAS_PRW_DATASF","parameter":"alpha_ATLAS_PRW_DATASF","type":"normsys"},{"constraint":"Gauss","data":{"hi":1.02,"lo":0.98},"name":"ATLAS_lumi","parameter":"alpha_ATLAS_lumi","type":"normsys"},{"constraint":"Gauss","data":{"hi":1.05,"lo":0.95},"name":"LQSignal_Acceptance_Var3c","parameter":"alpha_LQSignal_Acceptance_Var3c","type":"normsys"},{"constraint":"Gauss","data":{"hi":1.05,"lo":0.95},"name":"LQSignal_Acceptance_scale","parameter":"alpha_LQSignal_Acceptance_scale","type":"normsys"},{"constraint":"Gauss","data":{"hi":{"contents":[4.4154620241215685,9.986138036901941,11.195160074591442]},"lo":{"contents":[4.494681635278182,10.165303426144987,10.936775074191779]}},"name":"ATLAS_MU_SF_Isol_Stat","parameter":"alpha_ATLAS_MU_SF_Isol_Stat","type":"histosys"},{"constraint":"Gauss","data":{"hi":{"contents":[4.4164979631865355,9.988480946985657,11.191781225442758]},"lo":{"contents":[4.493692614501994,10.163066627835226,10.940000893277727]}},"name":"ATLAS_MU_SF_Isol_Syst","parameter":"alpha_ATLAS_MU_SF_Isol_Syst","type":"histosys"}],"name":"LQd_M600_B0p7"}],"type":"histfactory_dist"},{"axes":[{"max":4.0,"min":0.0,"name":"obs_x_CR_ttZ_3l0tau_njets4_HT_lep","nbins":4}],"name":"model_CR_ttZ_3l0tau_njets4_HT_lep","samples":[{"data":{"contents":[0.0921286866104514,0.7599025944916498,0.4232823519612451,0.3041939311209647]},"modifiers":[{"constraint_name":"lumiConstraint","name":"Lumi","parameter":"Lumi","type":"normfactor"},{"name":"SigXsecOverSM","parameter":"SigXsecOverSM","type":"normfactor"},{"constraint":"Gauss","data":{"hi":1.01326,"lo":0.986857},"name":"ATLAS_EL_SF_ID","parameter":"alpha_ATLAS_EL_SF_ID","type":"normsys"},{"constraint":"Gauss","data":{"hi":1.01523,"lo":0.984766},"name":"ATLAS_JES_Flavor_Comp","parameter":"alpha_ATLAS_JES_Flavor_Comp","type":"normsys"},{"constraint":"Gauss","data":{"hi":1.01168,"lo":0.98832},"name":"ATLAS_JES_PU_Rho","parameter":"alpha_ATLAS_JES_PU_Rho","type":"normsys"},{"constraint":"Gauss","data":{"hi":0.983229,"lo":1.01677},"name":"ATLAS_MU_MS","parameter":"alpha_ATLAS_MU_MS","type":"normsys"},{"constraint":"Gauss","data":{"hi":0.987881,"lo":1.01212},"name":"ATLAS_MU_RESBIAS","parameter":"alpha_ATLAS_MU_RESBIAS","type":"normsys"},{"constraint":"Gauss","data":{"hi":1.01226,"lo":0.987743},"name":"ATLAS_MU_SF_Isol_Stat","parameter":"alpha_ATLAS_MU_SF_Isol_Stat","type":"normsys"},{"constraint":"Gauss","data":{"hi":1.01701,"lo":0.983175},"name":"ATLAS_MU_SF_Isol_Syst","parameter":"alpha_ATLAS_MU_SF_Isol_Syst","type":"normsys"},{"constraint":"Gauss","data":{"hi":1.04094,"lo":0.959062},"name":"ATLAS_PRW_DATASF","parameter":"alpha_ATLAS_PRW_DATASF","type":"normsys"},{"constraint":"Gauss","data":{"hi":1.02,"lo":0.98},"name":"ATLAS_lumi","parameter":"alpha_ATLAS_lumi","type":"normsys"},{"constraint":"Gauss","data":{"hi":1.05,"lo":0.95},"name":"LQSignal_Acceptance_Var3c","parameter":"alpha_LQSignal_Acceptance_Var3c","type":"normsys"},{"constraint":"Gauss","data":{"hi":1.05,"lo":0.95},"name":"LQSignal_Acceptance_scale","parameter":"alpha_LQSignal_Acceptance_scale","type":"normsys"}],"name":"LQd_M600_B0p7"}],"type":"histfactory_dist"},{"axes":[{"max":5.0,"min":0.0,"name":"obs_x_SR_1l1tau_OS","nbins":5}],"name":"model_SR_1l1tau_OS","samples":[{"data":{"contents":[34.65491981657422,100.54534514757736,47.31703576682547,13.460094741580729,1.6790593434241456]},"modifiers":[{"constraint_name":"lumiConstraint","name":"Lumi","parameter":"Lumi","type":"normfactor"},{"name":"SigXsecOverSM","parameter":"SigXsecOverSM","type":"normfactor"},{"constraint":"Gauss","data":{"hi":1.01328,"lo":0.986724},"name":"ATLAS_JES_Flavor_Comp","parameter":"alpha_ATLAS_JES_Flavor_Comp","type":"normsys"},{"constraint":"Gauss","data":{"hi":1.01344,"lo":0.986561},"name":"ATLAS_JES_PU_Rho","parameter":"alpha_ATLAS_JES_PU_Rho","type":"normsys"},{"constraint":"Gauss","data":{"hi":0.826865,"lo":1.17314},"name":"ATLAS_MU_SCALE","parameter":"alpha_ATLAS_MU_SCALE","type":"normsys"},{"constraint":"Gauss","data":{"hi":1.0302,"lo":0.983497},"name":"ATLAS_TAU_SF_ELEOLR","parameter":"alpha_ATLAS_TAU_SF_ELEOLR","type":"normsys"},{"constraint":"Gauss","data":{"hi":1.01586,"lo":0.997837},"name":"ATLAS_TAU_SF_RECO","parameter":"alpha_ATLAS_TAU_SF_RECO","type":"normsys"},{"constraint":"Gauss","data":{"hi":1.05714,"lo":0.956557},"name":"ATLAS_TAU_SF_RECO_AFII","parameter":"alpha_ATLAS_TAU_SF_RECO_AFII","type":"normsys"},{"constraint":"Gauss","data":{"hi":1.01463,"lo":0.999072},"name":"ATLAS_TAU_SF_RNNID_1PGE40","parameter":"alpha_ATLAS_TAU_SF_RNNID_1PGE40","type":"normsys"},{"constraint":"Gauss","data":{"hi":1.01663,"lo":0.983372},"name":"ATLAS_TAU_SF_RNNID_HIGHPT","parameter":"alpha_ATLAS_TAU_SF_RNNID_HIGHPT","type":"normsys"},{"constraint":"Gauss","data":{"hi":1.02447,"lo":0.989234},"name":"ATLAS_TAU_SF_RNNID_SYST","parameter":"alpha_ATLAS_TAU_SF_RNNID_SYST","type":"normsys"},{"constraint":"Gauss","data":{"hi":1.03387,"lo":0.966128},"name":"ATLAS_TAU_TES_DET_HIGHPT_TAU_1p","parameter":"alpha_ATLAS_TAU_TES_DET_HIGHPT_TAU_1p","type":"normsys"},{"constraint":"Gauss","data":{"hi":1.01997,"lo":0.980033},"name":"ATLAS_TRUETAU_RW_STAT","parameter":"alpha_ATLAS_TRUETAU_RW_STAT","type":"normsys"},{"constraint":"Gauss","data":{"hi":1.02,"lo":0.98},"name":"ATLAS_lumi","parameter":"alpha_ATLAS_lumi","type":"normsys"},{"constraint":"Gauss","data":{"hi":1.081,"lo":0.919},"name":"LQSignal_Acceptance_Var3c","parameter":"alpha_LQSignal_Acceptance_Var3c","type":"normsys"},{"constraint":"Gauss","data":{"hi":1.027,"lo":0.973},"name":"LQSignal_Acceptance_scale","parameter":"alpha_LQSignal_Acceptance_scale","type":"normsys"},{"constraint":"Gauss","data":{"hi":{"contents":[33.71482179184359,100.3564727721093,48.08252057931031,13.78161594813572,1.7210237245830124]},"lo":{"contents":[35.61756996395615,100.73874598410129,46.533188448394675,13.13086185841011,1.6360885611196812]}},"name":"ATLAS_JES_Flavor_Comp","parameter":"alpha_ATLAS_JES_Flavor_Comp","type":"histosys"},{"constraint":"Gauss","data":{"hi":{"contents":[35.56973454737026,100.71835120145326,46.57570172098864,13.153163309609612,1.63950403656015]},"lo":{"contents":[33.749037021266155,100.3740276377703,48.05113189000535,13.764029746551039,1.7182285203890486]}},"name":"ATLAS_JES_Flavor_Resp","parameter":"alpha_ATLAS_JES_Flavor_Resp","type":"histosys"},{"constraint":"Gauss","data":{"hi":{"contents":[34.20880708872479,100.37478038550624,47.71912093178238,13.6491126065953,1.7046338033731905]},"lo":{"contents":[35.10718223684801,100.71826146488858,46.90940768272624,13.26847111430423,1.6531323172149088]}},"name":"ATLAS_JES_NP_Mod1","parameter":"alpha_ATLAS_JES_NP_Mod1","type":"histosys"},{"constraint":"Gauss","data":{"hi":{"contents":[34.366166258970594,100.36233335401103,47.61240576271204,13.615074665685382,1.7004747746028477]},"lo":{"contents":[34.94714939082509,100.73056003795176,47.01811010557733,13.303249168440797,1.6573861131869565]}},"name":"ATLAS_JES_PU_OffsetNPV","parameter":"alpha_ATLAS_JES_PU_OffsetNPV","type":"histosys"},{"constraint":"Gauss","data":{"hi":{"contents":[33.98263551771303,100.39051845778688,47.87196297269138,13.700251113130872,1.7110867546597919]},"lo":{"contents":[35.34389296959258,100.70401620913438,46.748332532110894,13.21397628636122,1.6462368187828929]}},"name":"ATLAS_JES_PU_Rho","parameter":"alpha_ATLAS_JES_PU_Rho","type":"histosys"},{"constraint":"Gauss","data":{"hi":{"contents":[33.81046188327153,100.01012832722851,48.1808434315899,13.913332538887728,1.741688635004261]},"lo":{"contents":[35.58045980044874,101.1319517122616,46.37028815443706,12.963338553892113,1.6104165949423737]}},"name":"ATLAS_TAU_TES_DET_HIGHPT_TAU_1p","parameter":"alpha_ATLAS_TAU_TES_DET_HIGHPT_TAU_1p","type":"histosys"}],"name":"LQd_M600_B0p7"}],"type":"histfactory_dist"},{"axes":[{"max":4.0,"min":0.0,"name":"obs_x_SR_1l1tau_SS","nbins":4}],"name":"model_SR_1l1tau_SS","samples":[{"data":{"contents":[11.205720468495135,23.73066233970263,10.848583993398302,2.9717966455373594]},"modifiers":[{"constraint_name":"lumiConstraint","name":"Lumi","parameter":"Lumi","type":"normfactor"},{"name":"SigXsecOverSM","parameter":"SigXsecOverSM","type":"normfactor"},{"constraint":"Gauss","data":{"hi":1.03071,"lo":0.983129},"name":"ATLAS_TAU_SF_ELEOLR","parameter":"alpha_ATLAS_TAU_SF_ELEOLR","type":"normsys"},{"constraint":"Gauss","data":{"hi":1.01583,"lo":0.998005},"name":"ATLAS_TAU_SF_RECO","parameter":"alpha_ATLAS_TAU_SF_RECO","type":"normsys"},{"constraint":"Gauss","data":{"hi":1.05719,"lo":0.956653},"name":"ATLAS_TAU_SF_RECO_AFII","parameter":"alpha_ATLAS_TAU_SF_RECO_AFII","type":"normsys"},{"constraint":"Gauss","data":{"hi":1.01484,"lo":0.998996},"name":"ATLAS_TAU_SF_RNNID_1PGE40","parameter":"alpha_ATLAS_TAU_SF_RNNID_1PGE40","type":"normsys"},{"constraint":"Gauss","data":{"hi":1.01665,"lo":0.983347},"name":"ATLAS_TAU_SF_RNNID_HIGHPT","parameter":"alpha_ATLAS_TAU_SF_RNNID_HIGHPT","type":"normsys"},{"constraint":"Gauss","data":{"hi":1.02445,"lo":0.989386},"name":"ATLAS_TAU_SF_RNNID_SYST","parameter":"alpha_ATLAS_TAU_SF_RNNID_SYST","type":"normsys"},{"constraint":"Gauss","data":{"hi":1.01453,"lo":0.985474},"name":"ATLAS_TAU_TES_DET_HIGHPT_TAU_1p","parameter":"alpha_ATLAS_TAU_TES_DET_HIGHPT_TAU_1p","type":"normsys"},{"constraint":"Gauss","data":{"hi":1.02042,"lo":0.979585},"name":"ATLAS_TRUETAU_RW_STAT","parameter":"alpha_ATLAS_TRUETAU_RW_STAT","type":"normsys"},{"constraint":"Gauss","data":{"hi":1.02,"lo":0.98},"name":"ATLAS_lumi","parameter":"alpha_ATLAS_lumi","type":"normsys"},{"constraint":"Gauss","data":{"hi":1.016,"lo":0.984},"name":"LQSignal_Acceptance_PDF_lowmass","parameter":"alpha_LQSignal_Acceptance_PDF_lowmass","type":"normsys"},{"constraint":"Gauss","data":{"hi":1.047,"lo":0.953},"name":"LQSignal_Acceptance_Var3c","parameter":"alpha_LQSignal_Acceptance_Var3c","type":"normsys"},{"constraint":"Gauss","data":{"hi":1.052,"lo":0.948},"name":"LQSignal_Acceptance_scale","parameter":"alpha_LQSignal_Acceptance_scale","type":"normsys"},{"constraint":"Gauss","data":{"hi":{"contents":[11.102653506178346,23.730833404951174,10.921009331264473,3.0022672047394274]},"lo":{"contents":[11.309295568739044,23.730490880337083,10.775801373094414,2.9411756249628795]}},"name":"ATLAS_JES_EtaInter_Model","parameter":"alpha_ATLAS_JES_EtaInter_Model","type":"histosys"},{"constraint":"Gauss","data":{"hi":{"contents":[10.997038090130685,23.740101246997824,10.990914377111784,3.0287097328931245]},"lo":{"contents":[11.416823108201916,23.721114334389668,10.704602710310612,2.914223294231231]}},"name":"ATLAS_JES_Flavor_Comp","parameter":"alpha_ATLAS_JES_Flavor_Comp","type":"histosys"},{"constraint":"Gauss","data":{"hi":{"contents":[11.394584566738745,23.725585806846343,10.718127191786557,2.9184658817617795]},"lo":{"contents":[11.01827602226962,23.735701145104642,10.978059973729573,3.0247263060295904]}},"name":"ATLAS_JES_Flavor_Resp","parameter":"alpha_ATLAS_JES_Flavor_Resp","type":"histosys"},{"constraint":"Gauss","data":{"hi":{"contents":[11.021910388901935,23.739984425008576,10.973472384762383,3.0213962484605315]},"lo":{"contents":[11.390643057736247,23.721284292439506,10.722939497564553,2.921896599393116]}},"name":"ATLAS_JES_NP_Mod1","parameter":"alpha_ATLAS_JES_NP_Mod1","type":"histosys"},{"constraint":"Gauss","data":{"hi":{"contents":[11.139894874495932,23.710486695475158,10.904457536138978,3.001924341023361]},"lo":{"contents":[11.272342067792403,23.75108234529386,10.792034609624498,2.9413044244226594]}},"name":"ATLAS_MU_SF_Isol_Stat","parameter":"alpha_ATLAS_MU_SF_Isol_Stat","type":"histosys"},{"constraint":"Gauss","data":{"hi":{"contents":[11.140379306307677,23.71056173952773,10.904081162807806,3.0017412384902076]},"lo":{"contents":[11.271950646734247,23.751036615962388,10.792331651803243,2.9414445326335503]}},"name":"ATLAS_MU_SF_Isol_Syst","parameter":"alpha_ATLAS_MU_SF_Isol_Syst","type":"histosys"},{"constraint":"Gauss","data":{"hi":{"contents":[11.127253311437544,23.70636377690211,10.915305553310748,3.0078408054830206]},"lo":{"contents":[11.28574498061587,23.755443161466303,10.780538195893376,2.935037109157874]}},"name":"ATLAS_PRW_DATASF","parameter":"alpha_ATLAS_PRW_DATASF","type":"histosys"},{"constraint":"Gauss","data":{"hi":{"contents":[11.091267564019502,23.69522023638976,10.945904663720535,3.0243709830036383]},"lo":{"contents":[11.324106445155293,23.767322379347828,10.747918984868344,2.9174156377619647]}},"name":"ATLAS_TAU_TES_DET_HIGHPT_TAU_1p","parameter":"alpha_ATLAS_TAU_TES_DET_HIGHPT_TAU_1p","type":"histosys"}],"name":"LQd_M600_B0p7"}],"type":"histfactory_dist"},{"axes":[{"max":4.0,"min":0.0,"name":"obs_x_SR_1l2tau","nbins":4}],"name":"model_SR_1l2tau","samples":[{"data":{"contents":[33.00345477811467,58.95598528620059,25.62418159931273,6.569974046084457]},"modifiers":[{"constraint_name":"lumiConstraint","name":"Lumi","parameter":"Lumi","type":"normfactor"},{"name":"SigXsecOverSM","parameter":"SigXsecOverSM","type":"normfactor"},{"constraint":"Gauss","data":{"hi":0.98752,"lo":1.01248},"name":"ATLAS_PRW_DATASF","parameter":"alpha_ATLAS_PRW_DATASF","type":"normsys"},{"constraint":"Gauss","data":{"hi":1.0582,"lo":0.970942},"name":"ATLAS_TAU_SF_ELEOLR","parameter":"alpha_ATLAS_TAU_SF_ELEOLR","type":"normsys"},{"constraint":"Gauss","data":{"hi":1.03252,"lo":0.995846},"name":"ATLAS_TAU_SF_RECO","parameter":"alpha_ATLAS_TAU_SF_RECO","type":"normsys"},{"constraint":"Gauss","data":{"hi":1.11925,"lo":0.914259},"name":"ATLAS_TAU_SF_RECO_AFII","parameter":"alpha_ATLAS_TAU_SF_RECO_AFII","type":"normsys"},{"constraint":"Gauss","data":{"hi":1.0141,"lo":1.0141},"name":"ATLAS_TAU_SF_RNNID_1P2530","parameter":"alpha_ATLAS_TAU_SF_RNNID_1P2530","type":"normsys"},{"constraint":"Gauss","data":{"hi":1.01412,"lo":1.01408},"name":"ATLAS_TAU_SF_RNNID_1P3040","parameter":"alpha_ATLAS_TAU_SF_RNNID_1P3040","type":"normsys"},{"constraint":"Gauss","data":{"hi":1.03043,"lo":0.997902},"name":"ATLAS_TAU_SF_RNNID_1PGE40","parameter":"alpha_ATLAS_TAU_SF_RNNID_1PGE40","type":"normsys"},{"constraint":"Gauss","data":{"hi":1.0141,"lo":1.0141},"name":"ATLAS_TAU_SF_RNNID_3P2530","parameter":"alpha_ATLAS_TAU_SF_RNNID_3P2530","type":"normsys"},{"constraint":"Gauss","data":{"hi":1.01411,"lo":1.01409},"name":"ATLAS_TAU_SF_RNNID_3P3040","parameter":"alpha_ATLAS_TAU_SF_RNNID_3P3040","type":"normsys"},{"constraint":"Gauss","data":{"hi":1.01902,"lo":1.00919},"name":"ATLAS_TAU_SF_RNNID_3PGE40","parameter":"alpha_ATLAS_TAU_SF_RNNID_3PGE40","type":"normsys"},{"constraint":"Gauss","data":{"hi":1.02324,"lo":0.976763},"name":"ATLAS_TAU_SF_RNNID_HIGHPT","parameter":"alpha_ATLAS_TAU_SF_RNNID_HIGHPT","type":"normsys"},{"constraint":"Gauss","data":{"hi":1.05004,"lo":0.978798},"name":"ATLAS_TAU_SF_RNNID_SYST","parameter":"alpha_ATLAS_TAU_SF_RNNID_SYST","type":"normsys"},{"constraint":"Gauss","data":{"hi":1.0141,"lo":1.0141},"name":"ATLAS_TAU_SF_TRUEELECTRON_ELEOLR_STAT","parameter":"alpha_ATLAS_TAU_SF_TRUEELECTRON_ELEOLR_STAT","type":"normsys"},{"constraint":"Gauss","data":{"hi":1.0141,"lo":1.0141},"name":"ATLAS_TAU_SF_TRUEELECTRON_ELEOLR_SYST","parameter":"alpha_ATLAS_TAU_SF_TRUEELECTRON_ELEOLR_SYST","type":"normsys"},{"constraint":"Gauss","data":{"hi":1.02254,"lo":0.977459},"name":"ATLAS_TAU_TES_DET_HIGHPT_TAU_1p","parameter":"alpha_ATLAS_TAU_TES_DET_HIGHPT_TAU_1p","type":"normsys"},{"constraint":"Gauss","data":{"hi":0.987073,"lo":1.01293},"name":"ATLAS_TAU_TES_DET_LOWPT_TAU","parameter":"alpha_ATLAS_TAU_TES_DET_LOWPT_TAU","type":"normsys"},{"constraint":"Gauss","data":{"hi":1.03458,"lo":0.966002},"name":"ATLAS_TRUETAU_RW_STAT","parameter":"alpha_ATLAS_TRUETAU_RW_STAT","type":"normsys"},{"constraint":"Gauss","data":{"hi":1.02,"lo":0.98},"name":"ATLAS_lumi","parameter":"alpha_ATLAS_lumi","type":"normsys"},{"constraint":"Gauss","data":{"hi":1.022,"lo":0.978},"name":"LQSignal_Acceptance_PDF_lowmass","parameter":"alpha_LQSignal_Acceptance_PDF_lowmass","type":"normsys"},{"constraint":"Gauss","data":{"hi":1.102,"lo":0.898},"name":"LQSignal_Acceptance_Var3c","parameter":"alpha_LQSignal_Acceptance_Var3c","type":"normsys"},{"constraint":"Gauss","data":{"hi":1.057,"lo":0.943},"name":"LQSignal_Acceptance_scale","parameter":"alpha_LQSignal_Acceptance_scale","type":"normsys"},{"constraint":"Gauss","data":{"hi":{"contents":[32.737165890497536,58.97119986370346,25.79791788167345,6.64731207383801]},"lo":{"contents":[33.27188389176633,58.94064733949225,25.44904932844565,6.492015150008221]}},"name":"ATLAS_JES_Flavor_Comp","parameter":"alpha_ATLAS_JES_Flavor_Comp","type":"histosys"},{"constraint":"Gauss","data":{"hi":{"contents":[33.37068187283779,58.93800310032646,25.383505159486116,6.461405577062069]},"lo":{"contents":[32.63702132720155,58.97392811090188,25.864338099313432,6.678308172295565]}},"name":"ATLAS_JES_Flavor_Resp","parameter":"alpha_ATLAS_JES_Flavor_Resp","type":"histosys"},{"constraint":"Gauss","data":{"hi":{"contents":[32.887351154016116,58.90800159250523,25.721146643510306,6.637096319680793]},"lo":{"contents":[33.119585044043326,59.00397806890408,25.527194933335984,6.502837663429059]}},"name":"ATLAS_JES_NP_Mix1","parameter":"alpha_ATLAS_JES_NP_Mix1","type":"histosys"},{"constraint":"Gauss","data":{"hi":{"contents":[32.76413225050493,58.96148175268645,25.78311443414216,6.644867272378917]},"lo":{"contents":[33.243899176308666,58.95046310667444,25.4645037181293,6.4947297086000315]}},"name":"ATLAS_JES_NP_Mod1","parameter":"alpha_ATLAS_JES_NP_Mod1","type":"histosys"},{"constraint":"Gauss","data":{"hi":{"contents":[32.79267963351459,58.94404936562405,25.770434593008353,6.646432117565443]},"lo":{"contents":[33.2161054937745,58.96802779071665,25.476627012162442,6.492835413058856]}},"name":"ATLAS_JES_PU_Rho","parameter":"alpha_ATLAS_JES_PU_Rho","type":"histosys"},{"constraint":"Gauss","data":{"hi":{"contents":[32.90422555159929,58.895936819229505,25.71402420397621,6.6394091349074476]},"lo":{"contents":[33.10291038273196,59.016169810502966,25.534134396529268,6.500381119948266]}},"name":"ATLAS_MU_SF_Isol_Stat","parameter":"alpha_ATLAS_MU_SF_Isol_Stat","type":"histosys"},{"constraint":"Gauss","data":{"hi":{"contents":[32.90621658755277,58.89687203262887,25.712326955287487,6.638180134243306]},"lo":{"contents":[33.10106839219946,59.01532676806178,25.535695926021543,6.5015046234296525]}},"name":"ATLAS_MU_SF_Isol_Syst","parameter":"alpha_ATLAS_MU_SF_Isol_Syst","type":"histosys"},{"constraint":"Gauss","data":{"hi":{"contents":[32.71644059509085,58.896428396751766,25.83991521559183,6.700811502277982]},"lo":{"contents":[33.3041958614366,59.018391130962826,25.39812999990566,6.432878717407364]}},"name":"ATLAS_TAU_SF_RNNID_HIGHPT","parameter":"alpha_ATLAS_TAU_SF_RNNID_HIGHPT","type":"histosys"},{"constraint":"Gauss","data":{"hi":{"contents":[31.938825845642643,59.035512404296895,26.315670982116497,6.8635864776564235]},"lo":{"contents":[34.12142232917475,58.872474019495776,24.89804810033518,6.2616512607067305]}},"name":"ATLAS_TAU_TES_DET_HIGHPT_TAU_1p","parameter":"alpha_ATLAS_TAU_TES_DET_HIGHPT_TAU_1p","type":"histosys"},{"constraint":"Gauss","data":{"hi":{"contents":[32.765204658982015,58.94088087843404,25.789423470985092,6.6580867013113005]},"lo":{"contents":[33.235369736664374,58.970688062064255,25.46333357137016,6.484204339613672]}},"name":"ATLAS_TAU_TES_DET_LOWPT_TAU","parameter":"alpha_ATLAS_TAU_TES_DET_LOWPT_TAU","type":"histosys"}],"name":"LQd_M600_B0p7"}],"type":"histfactory_dist"},{"axes":[{"max":5.0,"min":0.0,"name":"obs_x_SR_2lOS1tau_Meff","nbins":5}],"name":"model_SR_2lOS1tau_Meff","samples":[{"data":{"contents":[0.6929841726160231,10.758176304598507,20.269799016799865,12.468746145716388,8.860346148250223]},"modifiers":[{"constraint_name":"lumiConstraint","name":"Lumi","parameter":"Lumi","type":"normfactor"},{"name":"SigXsecOverSM","parameter":"SigXsecOverSM","type":"normfactor"},{"constraint":"Gauss","data":{"hi":1.01219,"lo":0.987905},"name":"ATLAS_EL_SF_ID","parameter":"alpha_ATLAS_EL_SF_ID","type":"normsys"},{"constraint":"Gauss","data":{"hi":1.03127,"lo":0.982776},"name":"ATLAS_TAU_SF_ELEOLR","parameter":"alpha_ATLAS_TAU_SF_ELEOLR","type":"normsys"},{"constraint":"Gauss","data":{"hi":1.01561,"lo":0.998437},"name":"ATLAS_TAU_SF_RECO","parameter":"alpha_ATLAS_TAU_SF_RECO","type":"normsys"},{"constraint":"Gauss","data":{"hi":1.05733,"lo":0.956715},"name":"ATLAS_TAU_SF_RECO_AFII","parameter":"alpha_ATLAS_TAU_SF_RECO_AFII","type":"normsys"},{"constraint":"Gauss","data":{"hi":1.01516,"lo":0.99889},"name":"ATLAS_TAU_SF_RNNID_1PGE40","parameter":"alpha_ATLAS_TAU_SF_RNNID_1PGE40","type":"normsys"},{"constraint":"Gauss","data":{"hi":1.01619,"lo":0.983811},"name":"ATLAS_TAU_SF_RNNID_HIGHPT","parameter":"alpha_ATLAS_TAU_SF_RNNID_HIGHPT","type":"normsys"},{"constraint":"Gauss","data":{"hi":1.02447,"lo":0.989576},"name":"ATLAS_TAU_SF_RNNID_SYST","parameter":"alpha_ATLAS_TAU_SF_RNNID_SYST","type":"normsys"},{"constraint":"Gauss","data":{"hi":1.02927,"lo":0.970732},"name":"ATLAS_TAU_TES_DET_HIGHPT_TAU_1p","parameter":"alpha_ATLAS_TAU_TES_DET_HIGHPT_TAU_1p","type":"normsys"},{"constraint":"Gauss","data":{"hi":1.02031,"lo":0.979692},"name":"ATLAS_TRUETAU_RW_STAT","parameter":"alpha_ATLAS_TRUETAU_RW_STAT","type":"normsys"},{"constraint":"Gauss","data":{"hi":1.02,"lo":0.98},"name":"ATLAS_lumi","parameter":"alpha_ATLAS_lumi","type":"normsys"},{"constraint":"Gauss","data":{"hi":1.032,"lo":0.968},"name":"LQSignal_Acceptance_PDF_lowmass","parameter":"alpha_LQSignal_Acceptance_PDF_lowmass","type":"normsys"},{"constraint":"Gauss","data":{"hi":1.103,"lo":0.897},"name":"LQSignal_Acceptance_Var3c","parameter":"alpha_LQSignal_Acceptance_Var3c","type":"normsys"},{"constraint":"Gauss","data":{"hi":1.069,"lo":0.931},"name":"LQSignal_Acceptance_scale","parameter":"alpha_LQSignal_Acceptance_scale","type":"normsys"},{"constraint":"Gauss","data":{"hi":{"contents":[0.6827208486683962,10.643350636837518,20.212873572207535,12.543834756448163,8.96727197381939]},"lo":{"contents":[0.7032736527609531,10.873294739443315,20.326869444013873,12.393465932976607,8.75314801878626]}},"name":"ATLAS_JES_Flavor_Comp","parameter":"alpha_ATLAS_JES_Flavor_Comp","type":"histosys"},{"constraint":"Gauss","data":{"hi":{"contents":[0.7045058867246724,10.885605820116833,20.329830612945877,12.384980531723622,8.74512893646999]},"lo":{"contents":[0.6814234140512879,10.630314983565734,20.20956402969364,12.55279560472081,8.97595375594953]}},"name":"ATLAS_JES_Flavor_Resp","parameter":"alpha_ATLAS_JES_Flavor_Resp","type":"histosys"},{"constraint":"Gauss","data":{"hi":{"contents":[0.6856393977489351,10.664988548491994,20.2104033754371,12.53086998151049,8.958150484792485]},"lo":{"contents":[0.700325238248123,10.85131734641288,20.329165275758285,12.406653430171922,8.762590497389796]}},"name":"ATLAS_JES_NP_Mod1","parameter":"alpha_ATLAS_JES_NP_Mod1","type":"histosys"},{"constraint":"Gauss","data":{"hi":{"contents":[0.6845228697341786,10.660300600251455,20.218124304579124,12.533396023756298,8.95370798965995]},"lo":{"contents":[0.7014850408575352,10.856509876135108,20.321715709714276,12.403793818830197,8.766547342443888]}},"name":"ATLAS_JES_PU_Rho","parameter":"alpha_ATLAS_JES_PU_Rho","type":"histosys"},{"constraint":"Gauss","data":{"hi":{"contents":[0.6878839689539205,10.684632780540477,20.19361441485295,12.50914346878509,8.974777154848567]},"lo":{"contents":[0.6981587430994198,10.832755254998071,20.34700196258898,12.42777227299098,8.744363554303549]}},"name":"ATLAS_MU_SF_Isol_Stat","parameter":"alpha_ATLAS_MU_SF_Isol_Stat","type":"histosys"},{"constraint":"Gauss","data":{"hi":{"contents":[0.6879913637645135,10.685973282794267,20.194682751725164,12.508365548885823,8.973038840811244]},"lo":{"contents":[0.6980700756916076,10.831616261280871,20.3460418986294,12.428425000005015,8.745898552374113]}},"name":"ATLAS_MU_SF_Isol_Syst","parameter":"alpha_ATLAS_MU_SF_Isol_Syst","type":"histosys"},{"constraint":"Gauss","data":{"hi":{"contents":[0.6810482659623537,10.626928608911314,20.18671602047157,12.545267098556343,9.010091794079424]},"lo":{"contents":[0.7056688269128323,10.897657456478933,20.358094419419224,12.387424935223676,8.701206149946337]}},"name":"ATLAS_TAU_TES_DET_HIGHPT_TAU_1p","parameter":"alpha_ATLAS_TAU_TES_DET_HIGHPT_TAU_1p","type":"histosys"}],"name":"LQd_M600_B0p7"}],"type":"histfactory_dist"},{"axes":[{"max":3.0,"min":0.0,"name":"obs_x_SR_2lOS2tau_Meff","nbins":3}],"name":"model_SR_2lOS2tau_Meff","samples":[{"data":{"contents":[0.02030999214971243,4.71356268193713,12.33299020697568]},"modifiers":[{"constraint_name":"lumiConstraint","name":"Lumi","parameter":"Lumi","type":"normfactor"},{"name":"SigXsecOverSM","parameter":"SigXsecOverSM","type":"normfactor"},{"constraint":"Gauss","data":{"hi":1.01064,"lo":0.989439},"name":"ATLAS_EL_SF_ID","parameter":"alpha_ATLAS_EL_SF_ID","type":"normsys"},{"constraint":"Gauss","data":{"hi":1.01187,"lo":0.990474},"name":"ATLAS_MU_SF_Isol_Stat","parameter":"alpha_ATLAS_MU_SF_Isol_Stat","type":"normsys"},{"constraint":"Gauss","data":{"hi":1.01372,"lo":0.98866},"name":"ATLAS_MU_SF_Isol_Syst","parameter":"alpha_ATLAS_MU_SF_Isol_Syst","type":"normsys"},{"constraint":"Gauss","data":{"hi":1.05461,"lo":0.97263},"name":"ATLAS_TAU_SF_ELEOLR","parameter":"alpha_ATLAS_TAU_SF_ELEOLR","type":"normsys"},{"constraint":"Gauss","data":{"hi":1.03081,"lo":0.995782},"name":"ATLAS_TAU_SF_RECO","parameter":"alpha_ATLAS_TAU_SF_RECO","type":"normsys"},{"constraint":"Gauss","data":{"hi":1.11434,"lo":0.916904},"name":"ATLAS_TAU_SF_RECO_AFII","parameter":"alpha_ATLAS_TAU_SF_RECO_AFII","type":"normsys"},{"constraint":"Gauss","data":{"hi":1.01322,"lo":1.01322},"name":"ATLAS_TAU_SF_RNNID_1P2530","parameter":"alpha_ATLAS_TAU_SF_RNNID_1P2530","type":"normsys"},{"constraint":"Gauss","data":{"hi":1.01333,"lo":1.01311},"name":"ATLAS_TAU_SF_RNNID_1P3040","parameter":"alpha_ATLAS_TAU_SF_RNNID_1P3040","type":"normsys"},{"constraint":"Gauss","data":{"hi":1.02863,"lo":0.997922},"name":"ATLAS_TAU_SF_RNNID_1PGE40","parameter":"alpha_ATLAS_TAU_SF_RNNID_1PGE40","type":"normsys"},{"constraint":"Gauss","data":{"hi":1.01325,"lo":1.01319},"name":"ATLAS_TAU_SF_RNNID_3P2530","parameter":"alpha_ATLAS_TAU_SF_RNNID_3P2530","type":"normsys"},{"constraint":"Gauss","data":{"hi":1.01327,"lo":1.01317},"name":"ATLAS_TAU_SF_RNNID_3P3040","parameter":"alpha_ATLAS_TAU_SF_RNNID_3P3040","type":"normsys"},{"constraint":"Gauss","data":{"hi":1.01777,"lo":1.00868},"name":"ATLAS_TAU_SF_RNNID_3PGE40","parameter":"alpha_ATLAS_TAU_SF_RNNID_3PGE40","type":"normsys"},{"constraint":"Gauss","data":{"hi":1.01921,"lo":0.980789},"name":"ATLAS_TAU_SF_RNNID_HIGHPT","parameter":"alpha_ATLAS_TAU_SF_RNNID_HIGHPT","type":"normsys"},{"constraint":"Gauss","data":{"hi":1.0474,"lo":0.979603},"name":"ATLAS_TAU_SF_RNNID_SYST","parameter":"alpha_ATLAS_TAU_SF_RNNID_SYST","type":"normsys"},{"constraint":"Gauss","data":{"hi":1.01322,"lo":1.01322},"name":"ATLAS_TAU_SF_TRUEELECTRON_ELEOLR_STAT","parameter":"alpha_ATLAS_TAU_SF_TRUEELECTRON_ELEOLR_STAT","type":"normsys"},{"constraint":"Gauss","data":{"hi":1.01322,"lo":1.01322},"name":"ATLAS_TAU_SF_TRUEELECTRON_ELEOLR_SYST","parameter":"alpha_ATLAS_TAU_SF_TRUEELECTRON_ELEOLR_SYST","type":"normsys"},{"constraint":"Gauss","data":{"hi":1.02042,"lo":0.979578},"name":"ATLAS_TAU_TES_DET_HIGHPT_TAU_1p","parameter":"alpha_ATLAS_TAU_TES_DET_HIGHPT_TAU_1p","type":"normsys"},{"constraint":"Gauss","data":{"hi":0.988976,"lo":1.01102},"name":"ATLAS_TAU_TES_DET_LOWPT_TAU","parameter":"alpha_ATLAS_TAU_TES_DET_LOWPT_TAU","type":"normsys"},{"constraint":"Gauss","data":{"hi":1.03207,"lo":0.968418},"name":"ATLAS_TRUETAU_RW_STAT","parameter":"alpha_ATLAS_TRUETAU_RW_STAT","type":"normsys"},{"constraint":"Gauss","data":{"hi":1.02,"lo":0.98},"name":"ATLAS_lumi","parameter":"alpha_ATLAS_lumi","type":"normsys"},{"constraint":"Gauss","data":{"hi":1.032,"lo":0.968},"name":"LQSignal_Acceptance_PDF_lowmass","parameter":"alpha_LQSignal_Acceptance_PDF_lowmass","type":"normsys"},{"constraint":"Gauss","data":{"hi":1.103,"lo":0.897},"name":"LQSignal_Acceptance_Var3c","parameter":"alpha_LQSignal_Acceptance_Var3c","type":"normsys"},{"constraint":"Gauss","data":{"hi":1.069,"lo":0.931},"name":"LQSignal_Acceptance_scale","parameter":"alpha_LQSignal_Acceptance_scale","type":"normsys"},{"constraint":"Gauss","data":{"hi":{"contents":[0.020075774101070146,4.70360750481302,12.343179602148435]},"lo":{"contents":[0.02054927565820804,4.72378695618856,12.322526649215758]}},"name":"ATLAS_TRUETAU_RW_STAT","parameter":"alpha_ATLAS_TRUETAU_RW_STAT","type":"histosys"}],"name":"LQd_M600_B0p7"}],"type":"histfactory_dist"},{"axes":[{"max":3.0,"min":0.0,"name":"obs_x_SR_2lSSor3l1tau_tauPt125_Meff","nbins":3}],"name":"model_SR_2lSSor3l1tau_tauPt125_Meff","samples":[{"data":{"contents":[6.295481612621584,11.924189573638849,3.5655922114961096]},"modifiers":[{"constraint_name":"lumiConstraint","name":"Lumi","parameter":"Lumi","type":"normfactor"},{"name":"SigXsecOverSM","parameter":"SigXsecOverSM","type":"normfactor"},{"constraint":"Gauss","data":{"hi":1.01188,"lo":0.988201},"name":"ATLAS_EL_SF_ID","parameter":"alpha_ATLAS_EL_SF_ID","type":"normsys"},{"constraint":"Gauss","data":{"hi":0.988079,"lo":1.01192},"name":"ATLAS_PRW_DATASF","parameter":"alpha_ATLAS_PRW_DATASF","type":"normsys"},{"constraint":"Gauss","data":{"hi":1.03113,"lo":0.982783},"name":"ATLAS_TAU_SF_ELEOLR","parameter":"alpha_ATLAS_TAU_SF_ELEOLR","type":"normsys"},{"constraint":"Gauss","data":{"hi":1.01542,"lo":0.998476},"name":"ATLAS_TAU_SF_RECO","parameter":"alpha_ATLAS_TAU_SF_RECO","type":"normsys"},{"constraint":"Gauss","data":{"hi":1.05841,"lo":0.955603},"name":"ATLAS_TAU_SF_RECO_AFII","parameter":"alpha_ATLAS_TAU_SF_RECO_AFII","type":"normsys"},{"constraint":"Gauss","data":{"hi":1.01483,"lo":0.99907},"name":"ATLAS_TAU_SF_RNNID_1PGE40","parameter":"alpha_ATLAS_TAU_SF_RNNID_1PGE40","type":"normsys"},{"constraint":"Gauss","data":{"hi":1.02492,"lo":0.988987},"name":"ATLAS_TAU_SF_RNNID_SYST","parameter":"alpha_ATLAS_TAU_SF_RNNID_SYST","type":"normsys"},{"constraint":"Gauss","data":{"hi":0.988086,"lo":1.01191},"name":"ATLAS_TAU_TES_DET_HIGHPT_TAU_3p","parameter":"alpha_ATLAS_TAU_TES_DET_HIGHPT_TAU_3p","type":"normsys"},{"constraint":"Gauss","data":{"hi":1.01847,"lo":0.981531},"name":"ATLAS_TRUETAU_RW_STAT","parameter":"alpha_ATLAS_TRUETAU_RW_STAT","type":"normsys"},{"constraint":"Gauss","data":{"hi":1.02,"lo":0.98},"name":"ATLAS_lumi","parameter":"alpha_ATLAS_lumi","type":"normsys"},{"constraint":"Gauss","data":{"hi":1.032,"lo":0.968},"name":"LQSignal_Acceptance_PDF_lowmass","parameter":"alpha_LQSignal_Acceptance_PDF_lowmass","type":"normsys"},{"constraint":"Gauss","data":{"hi":1.103,"lo":0.897},"name":"LQSignal_Acceptance_Var3c","parameter":"alpha_LQSignal_Acceptance_Var3c","type":"normsys"},{"constraint":"Gauss","data":{"hi":1.069,"lo":0.931},"name":"LQSignal_Acceptance_scale","parameter":"alpha_LQSignal_Acceptance_scale","type":"normsys"},{"constraint":"Gauss","data":{"hi":{"contents":[6.225795313074312,11.97783478685189,3.58163329783034]},"lo":{"contents":[6.365494396990464,11.870293029131425,3.5494759716346547]}},"name":"ATLAS_JES_BJES","parameter":"alpha_ATLAS_JES_BJES","type":"histosys"},{"constraint":"Gauss","data":{"hi":{"contents":[6.231075397004615,11.973770125217339,3.580417875534592]},"lo":{"contents":[6.359906809663234,11.874594409969024,3.550762178124287]}},"name":"ATLAS_JES_EtaInter_Model","parameter":"alpha_ATLAS_JES_EtaInter_Model","type":"histosys"},{"constraint":"Gauss","data":{"hi":{"contents":[6.360043023703776,11.87448955103269,3.550730823020077]},"lo":{"contents":[6.230943470962247,11.973871683209614,3.5804482435846836]}},"name":"ATLAS_JES_Flavor_Resp","parameter":"alpha_ATLAS_JES_Flavor_Resp","type":"histosys"},{"constraint":"Gauss","data":{"hi":{"contents":[6.232486292113177,11.972684003993914,3.5800931016494517]},"lo":{"contents":[6.358640812221151,11.875568987513661,3.5510535980217313]}},"name":"ATLAS_JES_PU_OffsetNPV","parameter":"alpha_ATLAS_JES_PU_OffsetNPV","type":"histosys"},{"constraint":"Gauss","data":{"hi":{"contents":[6.377571983621951,11.860995581653885,3.546695832480712]},"lo":{"contents":[6.213391244155181,11.987383563673149,3.5844885899282164]}},"name":"ATLAS_MET_Para","parameter":"alpha_ATLAS_MET_Para","type":"histosys"}],"name":"LQd_M600_B0p7"}],"type":"histfactory_dist"},{"axes":[{"max":3.0,"min":0.0,"name":"obs_x_SR_2lSSor3l1tau_tauPt225_Meff","nbins":3}],"name":"model_SR_2lSSor3l1tau_tauPt225_Meff","samples":[{"data":{"contents":[2.8037716837987183,13.264376292415253,5.197580688123899]},"modifiers":[{"constraint_name":"lumiConstraint","name":"Lumi","parameter":"Lumi","type":"normfactor"},{"name":"SigXsecOverSM","parameter":"SigXsecOverSM","type":"normfactor"},{"constraint":"Gauss","data":{"hi":1.01014,"lo":0.989918},"name":"ATLAS_EL_SF_ID","parameter":"alpha_ATLAS_EL_SF_ID","type":"normsys"},{"constraint":"Gauss","data":{"hi":1.01008,"lo":0.989953},"name":"ATLAS_MU_SF_Isol_Syst","parameter":"alpha_ATLAS_MU_SF_Isol_Syst","type":"normsys"},{"constraint":"Gauss","data":{"hi":0.98451,"lo":1.01549},"name":"ATLAS_PRW_DATASF","parameter":"alpha_ATLAS_PRW_DATASF","type":"normsys"},{"constraint":"Gauss","data":{"hi":1.03114,"lo":0.982928},"name":"ATLAS_TAU_SF_ELEOLR","parameter":"alpha_ATLAS_TAU_SF_ELEOLR","type":"normsys"},{"constraint":"Gauss","data":{"hi":1.01692,"lo":0.997134},"name":"ATLAS_TAU_SF_RECO","parameter":"alpha_ATLAS_TAU_SF_RECO","type":"normsys"},{"constraint":"Gauss","data":{"hi":1.05906,"lo":0.955146},"name":"ATLAS_TAU_SF_RECO_AFII","parameter":"alpha_ATLAS_TAU_SF_RECO_AFII","type":"normsys"},{"constraint":"Gauss","data":{"hi":1.01502,"lo":0.99903},"name":"ATLAS_TAU_SF_RNNID_1PGE40","parameter":"alpha_ATLAS_TAU_SF_RNNID_1PGE40","type":"normsys"},{"constraint":"Gauss","data":{"hi":1.02124,"lo":0.978764},"name":"ATLAS_TAU_SF_RNNID_HIGHPT","parameter":"alpha_ATLAS_TAU_SF_RNNID_HIGHPT","type":"normsys"},{"constraint":"Gauss","data":{"hi":1.02513,"lo":0.988934},"name":"ATLAS_TAU_SF_RNNID_SYST","parameter":"alpha_ATLAS_TAU_SF_RNNID_SYST","type":"normsys"},{"constraint":"Gauss","data":{"hi":1.04774,"lo":0.952259},"name":"ATLAS_TAU_TES_DET_HIGHPT_TAU_1p","parameter":"alpha_ATLAS_TAU_TES_DET_HIGHPT_TAU_1p","type":"normsys"},{"constraint":"Gauss","data":{"hi":1.02588,"lo":0.974117},"name":"ATLAS_TAU_TES_DET_HIGHPT_TAU_3p","parameter":"alpha_ATLAS_TAU_TES_DET_HIGHPT_TAU_3p","type":"normsys"},{"constraint":"Gauss","data":{"hi":1.02103,"lo":0.978978},"name":"ATLAS_TRUETAU_RW_STAT","parameter":"alpha_ATLAS_TRUETAU_RW_STAT","type":"normsys"},{"constraint":"Gauss","data":{"hi":1.02,"lo":0.98},"name":"ATLAS_lumi","parameter":"alpha_ATLAS_lumi","type":"normsys"},{"constraint":"Gauss","data":{"hi":1.032,"lo":0.968},"name":"LQSignal_Acceptance_PDF_lowmass","parameter":"alpha_LQSignal_Acceptance_PDF_lowmass","type":"normsys"},{"constraint":"Gauss","data":{"hi":1.103,"lo":0.897},"name":"LQSignal_Acceptance_Var3c","parameter":"alpha_LQSignal_Acceptance_Var3c","type":"normsys"},{"constraint":"Gauss","data":{"hi":1.069,"lo":0.931},"name":"LQSignal_Acceptance_scale","parameter":"alpha_LQSignal_Acceptance_scale","type":"normsys"}],"name":"LQd_M600_B0p7"}],"type":"histfactory_dist"}],"domains":[{"axes":[{"max":10.0,"min":0.0,"name":"Lumi"},{"max":10.0,"min":-0.005,"name":"SigXsecOverSM"},{"max":5.0,"min":-5.0,"name":"alpha_ATLAS_EG_SCALE"},{"max":5.0,"min":-5.0,"name":"alpha_ATLAS_EL_SF_ID"},{"max":5.0,"min":-5.0,"name":"alpha_ATLAS_FTAG_B0"},{"max":5.0,"min":-5.0,"name":"alpha_ATLAS_FTAG_B1"},{"max":5.0,"min":-5.0,"name":"alpha_ATLAS_FTAG_B3"},{"max":5.0,"min":-5.0,"name":"alpha_ATLAS_FTAG_C0"},{"max":5.0,"min":-5.0,"name":"alpha_ATLAS_FTAG_C1"},{"max":5.0,"min":-5.0,"name":"alpha_ATLAS_FTAG_EXTRAP_C"},{"max":5.0,"min":-5.0,"name":"alpha_ATLAS_JES_BJES"},{"max":5.0,"min":-5.0,"name":"alpha_ATLAS_JES_EtaInter_Model"},{"max":5.0,"min":-5.0,"name":"alpha_ATLAS_JES_EtaInter_NonClosurePosEta"},{"max":5.0,"min":-5.0,"name":"alpha_ATLAS_JES_EtaInter_Stat"},{"max":5.0,"min":-5.0,"name":"alpha_ATLAS_JES_Flavor_Comp"},{"max":5.0,"min":-5.0,"name":"alpha_ATLAS_JES_Flavor_Resp"},{"max":5.0,"min":-5.0,"name":"alpha_ATLAS_JES_NP_Det1"},{"max":5.0,"min":-5.0,"name":"alpha_ATLAS_JES_NP_Mix1"},{"max":5.0,"min":-5.0,"name":"alpha_ATLAS_JES_NP_Mix2"},{"max":5.0,"min":-5.0,"name":"alpha_ATLAS_JES_NP_Mod1"},{"max":5.0,"min":-5.0,"name":"alpha_ATLAS_JES_NP_Mod2"},{"max":5.0,"min":-5.0,"name":"alpha_ATLAS_JES_NP_Mod3"},{"max":5.0,"min":-5.0,"name":"alpha_ATLAS_JES_NP_Mod4"},{"max":5.0,"min":-5.0,"name":"alpha_ATLAS_JES_NP_Stat1"},{"max":5.0,"min":-5.0,"name":"alpha_ATLAS_JES_NP_Stat3"},{"max":5.0,"min":-5.0,"name":"alpha_ATLAS_JES_NP_Stat4"},{"max":5.0,"min":-5.0,"name":"alpha_ATLAS_JES_PU_OffsetMu"},{"max":5.0,"min":-5.0,"name":"alpha_ATLAS_JES_PU_OffsetNPV"},{"max":5.0,"min":-5.0,"name":"alpha_ATLAS_JES_PU_PtTerm"},{"max":5.0,"min":-5.0,"name":"alpha_ATLAS_JES_PU_Rho"},{"max":5.0,"min":-5.0,"name":"alpha_ATLAS_JVT"},{"max":5.0,"min":-5.0,"name":"alpha_ATLAS_MET_Para"},{"max":5.0,"min":-5.0,"name":"alpha_ATLAS_MET_Perp"},{"max":5.0,"min":-5.0,"name":"alpha_ATLAS_MET_Scale"},{"max":5.0,"min":-5.0,"name":"alpha_ATLAS_MU_MS"},{"max":5.0,"min":-5.0,"name":"alpha_ATLAS_MU_RESBIAS"},{"max":5.0,"min":-5.0,"name":"alpha_ATLAS_MU_SCALE"},{"max":5.0,"min":-5.0,"name":"alpha_ATLAS_MU_SF_Isol_Stat"},{"max":5.0,"min":-5.0,"name":"alpha_ATLAS_MU_SF_Isol_Syst"},{"max":5.0,"min":-5.0,"name":"alpha_ATLAS_PRW_DATASF"},{"max":5.0,"min":-5.0,"name":"alpha_ATLAS_TAU_SF_ELEOLR"},{"max":5.0,"min":-5.0,"name":"alpha_ATLAS_TAU_SF_RECO"},{"max":5.0,"min":-5.0,"name":"alpha_ATLAS_TAU_SF_RECO_AFII"},{"max":5.0,"min":-5.0,"name":"alpha_ATLAS_TAU_SF_RNNID_1P2530"},{"max":5.0,"min":-5.0,"name":"alpha_ATLAS_TAU_SF_RNNID_1P3040"},{"max":5.0,"min":-5.0,"name":"alpha_ATLAS_TAU_SF_RNNID_1PGE40"},{"max":5.0,"min":-5.0,"name":"alpha_ATLAS_TAU_SF_RNNID_3P2530"},{"max":5.0,"min":-5.0,"name":"alpha_ATLAS_TAU_SF_RNNID_3P3040"},{"max":5.0,"min":-5.0,"name":"alpha_ATLAS_TAU_SF_RNNID_3PGE40"},{"max":5.0,"min":-5.0,"name":"alpha_ATLAS_TAU_SF_RNNID_HIGHPT"},{"max":5.0,"min":-5.0,"name":"alpha_ATLAS_TAU_SF_RNNID_SYST"},{"max":5.0,"min":-5.0,"name":"alpha_ATLAS_TAU_SF_TRUEELECTRON_ELEOLR_STAT"},{"max":5.0,"min":-5.0,"name":"alpha_ATLAS_TAU_SF_TRUEELECTRON_ELEOLR_SYST"},{"max":5.0,"min":-5.0,"name":"alpha_ATLAS_TAU_TES_DET_HIGHPT_TAU_1p"},{"max":5.0,"min":-5.0,"name":"alpha_ATLAS_TAU_TES_DET_HIGHPT_TAU_3p"},{"max":5.0,"min":-5.0,"name":"alpha_ATLAS_TAU_TES_DET_LOWPT_TAU"},{"max":5.0,"min":-5.0,"name":"alpha_ATLAS_TRUETAU_RW_STAT"},{"max":5.0,"min":-5.0,"name":"alpha_ATLAS_lumi"},{"max":5.0,"min":-5.0,"name":"alpha_LQSignal_Acceptance_PDF_lowmass"},{"max":5.0,"min":-5.0,"name":"alpha_LQSignal_Acceptance_Var3c"},{"max":5.0,"min":-5.0,"name":"alpha_LQSignal_Acceptance_scale"},{"max":2.000000014901161,"min":0.0,"name":"nominalLumi"},{"max":1.0,"min":0.0,"name":"obs_x_CR_ExtCo_2lSS0tau_Nevt"},{"max":1.0,"min":0.0,"name":"obs_x_CR_ExtCo_3l0tau_Nevt"},{"max":3.0,"min":0.0,"name":"obs_x_CR_HFe_2lSS0tau_neg_HT_lep"},{"max":3.0,"min":0.0,"name":"obs_x_CR_HFe_2lSS0tau_pos_HT_lep"},{"max":3.0,"min":0.0,"name":"obs_x_CR_HFmu_2lSS0tau_neg_HT_lep"},{"max":3.0,"min":0.0,"name":"obs_x_CR_HFmu_2lSS0tau_pos_HT_lep"},{"max":1.0,"min":0.0,"name":"obs_x_CR_IntCo_2lSS0tau_Nevt"},{"max":1.0,"min":0.0,"name":"obs_x_CR_IntCo_3l0tau_Nevt"},{"max":1.0,"min":0.0,"name":"obs_x_CR_LowMeff_ttbar_1l1tau_OS"},{"max":1.0,"min":0.0,"name":"obs_x_CR_LowMeff_ttbar_1l1tau_SS"},{"max":1.0,"min":0.0,"name":"obs_x_CR_LowMeff_ttbar_1l2tau"},{"max":4.0,"min":0.0,"name":"obs_x_CR_VV_3l0tau_2or3j_HT_lep"},{"max":3.0,"min":0.0,"name":"obs_x_CR_ttW_2lSS0tau_neg_HT_lep"},{"max":3.0,"min":0.0,"name":"obs_x_CR_ttW_2lSS0tau_pos_HT_lep"},{"max":4.0,"min":0.0,"name":"obs_x_CR_ttZ_3l0tau_njets4_HT_lep"},{"max":5.0,"min":0.0,"name":"obs_x_SR_1l1tau_OS"},{"max":4.0,"min":0.0,"name":"obs_x_SR_1l1tau_SS"},{"max":4.0,"min":0.0,"name":"obs_x_SR_1l2tau"},{"max":5.0,"min":0.0,"name":"obs_x_SR_2lOS1tau_Meff"},{"max":3.0,"min":0.0,"name":"obs_x_SR_2lOS2tau_Meff"},{"max":3.0,"min":0.0,"name":"obs_x_SR_2lSSor3l1tau_tauPt125_Meff"},{"max":3.0,"min":0.0,"name":"obs_x_SR_2lSSor3l1tau_tauPt225_Meff"}],"name":"default_domain","type":"product_domain"}],"likelihoods":[{"data":["asimovData_CR_ExtCo_2lSS0tau_Nevt","asimovData_CR_ExtCo_3l0tau_Nevt","asimovData_CR_HFe_2lSS0tau_neg_HT_lep","asimovData_CR_HFe_2lSS0tau_pos_HT_lep","asimovData_CR_HFmu_2lSS0tau_neg_HT_lep","asimovData_CR_HFmu_2lSS0tau_pos_HT_lep","asimovData_CR_IntCo_2lSS0tau_Nevt","asimovData_CR_IntCo_3l0tau_Nevt","asimovData_CR_LowMeff_ttbar_1l1tau_OS","asimovData_CR_LowMeff_ttbar_1l1tau_SS","asimovData_CR_LowMeff_ttbar_1l2tau","asimovData_CR_VV_3l0tau_2or3j_HT_lep","asimovData_CR_ttW_2lSS0tau_neg_HT_lep","asimovData_CR_ttW_2lSS0tau_pos_HT_lep","asimovData_CR_ttZ_3l0tau_njets4_HT_lep","asimovData_SR_1l1tau_OS","asimovData_SR_1l1tau_SS","asimovData_SR_1l2tau","asimovData_SR_2lOS1tau_Meff","asimovData_SR_2lOS2tau_Meff","asimovData_SR_2lSSor3l1tau_tauPt125_Meff","asimovData_SR_2lSSor3l1tau_tauPt225_Meff"],"distributions":["model_CR_ExtCo_2lSS0tau_Nevt","model_CR_ExtCo_3l0tau_Nevt","model_CR_HFe_2lSS0tau_neg_HT_lep","model_CR_HFe_2lSS0tau_pos_HT_lep","model_CR_HFmu_2lSS0tau_neg_HT_lep","model_CR_HFmu_2lSS0tau_pos_HT_lep","model_CR_IntCo_2lSS0tau_Nevt","model_CR_IntCo_3l0tau_Nevt","model_CR_LowMeff_ttbar_1l1tau_OS","model_CR_LowMeff_ttbar_1l1tau_SS","model_CR_LowMeff_ttbar_1l2tau","model_CR_VV_3l0tau_2or3j_HT_lep","model_CR_ttW_2lSS0tau_neg_HT_lep","model_CR_ttW_2lSS0tau_pos_HT_lep","model_CR_ttZ_3l0tau_njets4_HT_lep","model_SR_1l1tau_OS","model_SR_1l1tau_SS","model_SR_1l2tau","model_SR_2lOS1tau_Meff","model_SR_2lOS2tau_Meff","model_SR_2lSSor3l1tau_tauPt125_Meff","model_SR_2lSSor3l1tau_tauPt225_Meff"],"name":"simPdf_asimovData"},{"data":["obsData_CR_ExtCo_2lSS0tau_Nevt","obsData_CR_ExtCo_3l0tau_Nevt","obsData_CR_HFe_2lSS0tau_neg_HT_lep","obsData_CR_HFe_2lSS0tau_pos_HT_lep","obsData_CR_HFmu_2lSS0tau_neg_HT_lep","obsData_CR_HFmu_2lSS0tau_pos_HT_lep","obsData_CR_IntCo_2lSS0tau_Nevt","obsData_CR_IntCo_3l0tau_Nevt","obsData_CR_LowMeff_ttbar_1l1tau_OS","obsData_CR_LowMeff_ttbar_1l1tau_SS","obsData_CR_LowMeff_ttbar_1l2tau","obsData_CR_VV_3l0tau_2or3j_HT_lep","obsData_CR_ttW_2lSS0tau_neg_HT_lep","obsData_CR_ttW_2lSS0tau_pos_HT_lep","obsData_CR_ttZ_3l0tau_njets4_HT_lep","obsData_SR_1l1tau_OS","obsData_SR_1l1tau_SS","obsData_SR_1l2tau","obsData_SR_2lOS1tau_Meff","obsData_SR_2lOS2tau_Meff","obsData_SR_2lSSor3l1tau_tauPt125_Meff","obsData_SR_2lSSor3l1tau_tauPt225_Meff"],"distributions":["model_CR_ExtCo_2lSS0tau_Nevt","model_CR_ExtCo_3l0tau_Nevt","model_CR_HFe_2lSS0tau_neg_HT_lep","model_CR_HFe_2lSS0tau_pos_HT_lep","model_CR_HFmu_2lSS0tau_neg_HT_lep","model_CR_HFmu_2lSS0tau_pos_HT_lep","model_CR_IntCo_2lSS0tau_Nevt","model_CR_IntCo_3l0tau_Nevt","model_CR_LowMeff_ttbar_1l1tau_OS","model_CR_LowMeff_ttbar_1l1tau_SS","model_CR_LowMeff_ttbar_1l2tau","model_CR_VV_3l0tau_2or3j_HT_lep","model_CR_ttW_2lSS0tau_neg_HT_lep","model_CR_ttW_2lSS0tau_pos_HT_lep","model_CR_ttZ_3l0tau_njets4_HT_lep","model_SR_1l1tau_OS","model_SR_1l1tau_SS","model_SR_1l2tau","model_SR_2lOS1tau_Meff","model_SR_2lOS2tau_Meff","model_SR_2lSSor3l1tau_tauPt125_Meff","model_SR_2lSSor3l1tau_tauPt225_Meff"],"name":"simPdf_obsData"}],"metadata":{"hs3_version":"0.2","packages":[{"name":"ROOT","version":"6.32.02"}]},"misc":{"ROOT_internal":{"ModelConfigs":{"simPdf_asimovData":{"mcName":"ModelConfig","pdfName":"simPdf"},"simPdf_obsData":{"mcName":"ModelConfig","pdfName":"simPdf"}},"attributes":{"CR_ExtCo_2lSS0tau_Nevt_model":{"tags":["BinnedLikelihood","GenerateBinned"]},"CR_ExtCo_3l0tau_Nevt_model":{"tags":["BinnedLikelihood","GenerateBinned"]},"CR_HFe_2lSS0tau_neg_HT_lep_model":{"tags":["BinnedLikelihood","GenerateBinned"]},"CR_HFe_2lSS0tau_pos_HT_lep_model":{"tags":["BinnedLikelihood","GenerateBinned"]},"CR_HFmu_2lSS0tau_neg_HT_lep_model":{"tags":["BinnedLikelihood","GenerateBinned"]},"CR_HFmu_2lSS0tau_pos_HT_lep_model":{"tags":["BinnedLikelihood","GenerateBinned"]},"CR_IntCo_2lSS0tau_Nevt_model":{"tags":["BinnedLikelihood","GenerateBinned"]},"CR_IntCo_3l0tau_Nevt_model":{"tags":["BinnedLikelihood","GenerateBinned"]},"CR_LowMeff_ttbar_1l1tau_OS_model":{"tags":["BinnedLikelihood","GenerateBinned"]},"CR_LowMeff_ttbar_1l1tau_SS_model":{"tags":["BinnedLikelihood","GenerateBinned"]},"CR_LowMeff_ttbar_1l2tau_model":{"tags":["BinnedLikelihood","GenerateBinned"]},"CR_VV_3l0tau_2or3j_HT_lep_model":{"tags":["BinnedLikelihood","GenerateBinned"]},"CR_ttW_2lSS0tau_neg_HT_lep_model":{"tags":["BinnedLikelihood","GenerateBinned"]},"CR_ttW_2lSS0tau_pos_HT_lep_model":{"tags":["BinnedLikelihood","GenerateBinned"]},"CR_ttZ_3l0tau_njets4_HT_lep_model":{"tags":["BinnedLikelihood","GenerateBinned"]},"Lumi":{"tags":["Constant"]},"SR_1l1tau_OS_model":{"tags":["BinnedLikelihood","GenerateBinned"]},"SR_1l1tau_SS_model":{"tags":["BinnedLikelihood","GenerateBinned"]},"SR_1l2tau_model":{"tags":["BinnedLikelihood","GenerateBinned"]},"SR_2lOS1tau_Meff_model":{"tags":["BinnedLikelihood","GenerateBinned"]},"SR_2lOS2tau_Meff_model":{"tags":["BinnedLikelihood","GenerateBinned"]},"SR_2lSSor3l1tau_tauPt125_Meff_model":{"tags":["BinnedLikelihood","GenerateBinned"]},"SR_2lSSor3l1tau_tauPt225_Meff_model":{"tags":["BinnedLikelihood","GenerateBinned"]},"nom_alpha_ATLAS_EG_SCALE":{"tags":["Constant"]},"nom_alpha_ATLAS_EL_SF_ID":{"tags":["Constant"]},"nom_alpha_ATLAS_FTAG_B0":{"tags":["Constant"]},"nom_alpha_ATLAS_FTAG_B1":{"tags":["Constant"]},"nom_alpha_ATLAS_FTAG_B3":{"tags":["Constant"]},"nom_alpha_ATLAS_FTAG_C0":{"tags":["Constant"]},"nom_alpha_ATLAS_FTAG_C1":{"tags":["Constant"]},"nom_alpha_ATLAS_FTAG_EXTRAP_C":{"tags":["Constant"]},"nom_alpha_ATLAS_JES_BJES":{"tags":["Constant"]},"nom_alpha_ATLAS_JES_EtaInter_Model":{"tags":["Constant"]},"nom_alpha_ATLAS_JES_EtaInter_NonClosurePosEta":{"tags":["Constant"]},"nom_alpha_ATLAS_JES_EtaInter_Stat":{"tags":["Constant"]},"nom_alpha_ATLAS_JES_Flavor_Comp":{"tags":["Constant"]},"nom_alpha_ATLAS_JES_Flavor_Resp":{"tags":["Constant"]},"nom_alpha_ATLAS_JES_NP_Det1":{"tags":["Constant"]},"nom_alpha_ATLAS_JES_NP_Mix1":{"tags":["Constant"]},"nom_alpha_ATLAS_JES_NP_Mix2":{"tags":["Constant"]},"nom_alpha_ATLAS_JES_NP_Mod1":{"tags":["Constant"]},"nom_alpha_ATLAS_JES_NP_Mod2":{"tags":["Constant"]},"nom_alpha_ATLAS_JES_NP_Mod3":{"tags":["Constant"]},"nom_alpha_ATLAS_JES_NP_Mod4":{"tags":["Constant"]},"nom_alpha_ATLAS_JES_NP_Stat1":{"tags":["Constant"]},"nom_alpha_ATLAS_JES_NP_Stat3":{"tags":["Constant"]},"nom_alpha_ATLAS_JES_NP_Stat4":{"tags":["Constant"]},"nom_alpha_ATLAS_JES_PU_OffsetMu":{"tags":["Constant"]},"nom_alpha_ATLAS_JES_PU_OffsetNPV":{"tags":["Constant"]},"nom_alpha_ATLAS_JES_PU_PtTerm":{"tags":["Constant"]},"nom_alpha_ATLAS_JES_PU_Rho":{"tags":["Constant"]},"nom_alpha_ATLAS_JVT":{"tags":["Constant"]},"nom_alpha_ATLAS_MET_Para":{"tags":["Constant"]},"nom_alpha_ATLAS_MET_Perp":{"tags":["Constant"]},"nom_alpha_ATLAS_MET_Scale":{"tags":["Constant"]},"nom_alpha_ATLAS_MU_MS":{"tags":["Constant"]},"nom_alpha_ATLAS_MU_RESBIAS":{"tags":["Constant"]},"nom_alpha_ATLAS_MU_SCALE":{"tags":["Constant"]},"nom_alpha_ATLAS_MU_SF_Isol_Stat":{"tags":["Constant"]},"nom_alpha_ATLAS_MU_SF_Isol_Syst":{"tags":["Constant"]},"nom_alpha_ATLAS_PRW_DATASF":{"tags":["Constant"]},"nom_alpha_ATLAS_TAU_SF_ELEOLR":{"tags":["Constant"]},"nom_alpha_ATLAS_TAU_SF_RECO":{"tags":["Constant"]},"nom_alpha_ATLAS_TAU_SF_RECO_AFII":{"tags":["Constant"]},"nom_alpha_ATLAS_TAU_SF_RNNID_1P2530":{"tags":["Constant"]},"nom_alpha_ATLAS_TAU_SF_RNNID_1P3040":{"tags":["Constant"]},"nom_alpha_ATLAS_TAU_SF_RNNID_1PGE40":{"tags":["Constant"]},"nom_alpha_ATLAS_TAU_SF_RNNID_3P2530":{"tags":["Constant"]},"nom_alpha_ATLAS_TAU_SF_RNNID_3P3040":{"tags":["Constant"]},"nom_alpha_ATLAS_TAU_SF_RNNID_3PGE40":{"tags":["Constant"]},"nom_alpha_ATLAS_TAU_SF_RNNID_HIGHPT":{"tags":["Constant"]},"nom_alpha_ATLAS_TAU_SF_RNNID_SYST":{"tags":["Constant"]},"nom_alpha_ATLAS_TAU_SF_TRUEELECTRON_ELEOLR_STAT":{"tags":["Constant"]},"nom_alpha_ATLAS_TAU_SF_TRUEELECTRON_ELEOLR_SYST":{"tags":["Constant"]},"nom_alpha_ATLAS_TAU_TES_DET_HIGHPT_TAU_1p":{"tags":["Constant"]},"nom_alpha_ATLAS_TAU_TES_DET_HIGHPT_TAU_3p":{"tags":["Constant"]},"nom_alpha_ATLAS_TAU_TES_DET_LOWPT_TAU":{"tags":["Constant"]},"nom_alpha_ATLAS_TRUETAU_RW_STAT":{"tags":["Constant"]},"nom_alpha_ATLAS_lumi":{"tags":["Constant"]},"nom_alpha_LQSignal_Acceptance_PDF_lowmass":{"tags":["Constant"]},"nom_alpha_LQSignal_Acceptance_Var3c":{"tags":["Constant"]},"nom_alpha_LQSignal_Acceptance_scale":{"tags":["Constant"]},"nominalLumi":{"tags":["Constant"]}},"combined_datasets":{"asimovData":{"index_cat":"channelCat","indices":[17,21,13,12,15,14,16,20,7,8,9,18,11,10,19,0,1,2,3,4,5,6],"labels":["CR_ExtCo_2lSS0tau_Nevt","CR_ExtCo_3l0tau_Nevt","CR_HFe_2lSS0tau_neg_HT_lep","CR_HFe_2lSS0tau_pos_HT_lep","CR_HFmu_2lSS0tau_neg_HT_lep","CR_HFmu_2lSS0tau_pos_HT_lep","CR_IntCo_2lSS0tau_Nevt","CR_IntCo_3l0tau_Nevt","CR_LowMeff_ttbar_1l1tau_OS","CR_LowMeff_ttbar_1l1tau_SS","CR_LowMeff_ttbar_1l2tau","CR_VV_3l0tau_2or3j_HT_lep","CR_ttW_2lSS0tau_neg_HT_lep","CR_ttW_2lSS0tau_pos_HT_lep","CR_ttZ_3l0tau_njets4_HT_lep","SR_1l1tau_OS","SR_1l1tau_SS","SR_1l2tau","SR_2lOS1tau_Meff","SR_2lOS2tau_Meff","SR_2lSSor3l1tau_tauPt125_Meff","SR_2lSSor3l1tau_tauPt225_Meff"]},"obsData":{"index_cat":"channelCat","indices":[17,21,13,12,15,14,16,20,7,8,9,18,11,10,19,0,1,2,3,4,5,6],"labels":["CR_ExtCo_2lSS0tau_Nevt","CR_ExtCo_3l0tau_Nevt","CR_HFe_2lSS0tau_neg_HT_lep","CR_HFe_2lSS0tau_pos_HT_lep","CR_HFmu_2lSS0tau_neg_HT_lep","CR_HFmu_2lSS0tau_pos_HT_lep","CR_IntCo_2lSS0tau_Nevt","CR_IntCo_3l0tau_Nevt","CR_LowMeff_ttbar_1l1tau_OS","CR_LowMeff_ttbar_1l1tau_SS","CR_LowMeff_ttbar_1l2tau","CR_VV_3l0tau_2or3j_HT_lep","CR_ttW_2lSS0tau_neg_HT_lep","CR_ttW_2lSS0tau_pos_HT_lep","CR_ttZ_3l0tau_njets4_HT_lep","SR_1l1tau_OS","SR_1l1tau_SS","SR_1l2tau","SR_2lOS1tau_Meff","SR_2lOS2tau_Meff","SR_2lSSor3l1tau_tauPt125_Meff","SR_2lSSor3l1tau_tauPt225_Meff"]}},"combined_distributions":{"simPdf":{"distributions":["model_CR_ExtCo_2lSS0tau_Nevt","model_CR_ExtCo_3l0tau_Nevt","model_CR_HFe_2lSS0tau_neg_HT_lep","model_CR_HFe_2lSS0tau_pos_HT_lep","model_CR_HFmu_2lSS0tau_neg_HT_lep","model_CR_HFmu_2lSS0tau_pos_HT_lep","model_CR_IntCo_2lSS0tau_Nevt","model_CR_IntCo_3l0tau_Nevt","model_CR_LowMeff_ttbar_1l1tau_OS","model_CR_LowMeff_ttbar_1l1tau_SS","model_CR_LowMeff_ttbar_1l2tau","model_CR_VV_3l0tau_2or3j_HT_lep","model_CR_ttW_2lSS0tau_neg_HT_lep","model_CR_ttW_2lSS0tau_pos_HT_lep","model_CR_ttZ_3l0tau_njets4_HT_lep","model_SR_1l1tau_OS","model_SR_1l1tau_SS","model_SR_1l2tau","model_SR_2lOS1tau_Meff","model_SR_2lOS2tau_Meff","model_SR_2lSSor3l1tau_tauPt125_Meff","model_SR_2lSSor3l1tau_tauPt225_Meff"],"index_cat":"channelCat","indices":[17,21,13,12,15,14,16,20,7,8,9,18,11,10,19,0,1,2,3,4,5,6],"labels":["CR_ExtCo_2lSS0tau_Nevt","CR_ExtCo_3l0tau_Nevt","CR_HFe_2lSS0tau_neg_HT_lep","CR_HFe_2lSS0tau_pos_HT_lep","CR_HFmu_2lSS0tau_neg_HT_lep","CR_HFmu_2lSS0tau_pos_HT_lep","CR_IntCo_2lSS0tau_Nevt","CR_IntCo_3l0tau_Nevt","CR_LowMeff_ttbar_1l1tau_OS","CR_LowMeff_ttbar_1l1tau_SS","CR_LowMeff_ttbar_1l2tau","CR_VV_3l0tau_2or3j_HT_lep","CR_ttW_2lSS0tau_neg_HT_lep","CR_ttW_2lSS0tau_pos_HT_lep","CR_ttZ_3l0tau_njets4_HT_lep","SR_1l1tau_OS","SR_1l1tau_SS","SR_1l2tau","SR_2lOS1tau_Meff","SR_2lOS2tau_Meff","SR_2lSSor3l1tau_tauPt125_Meff","SR_2lSSor3l1tau_tauPt225_Meff"]}}}},"parameter_points":[{"name":"default_values","parameters":[{"const":true,"name":"Lumi","value":1.0},{"name":"SigXsecOverSM","value":0.0},{"name":"alpha_ATLAS_EL_SF_ID","value":0.0},{"name":"alpha_ATLAS_MU_SF_Isol_Stat","value":0.0},{"name":"alpha_ATLAS_MU_SF_Isol_Syst","value":0.0},{"name":"alpha_ATLAS_PRW_DATASF","value":0.0},{"name":"alpha_ATLAS_lumi","value":0.0},{"name":"alpha_LQSignal_Acceptance_PDF_lowmass","value":0.0},{"name":"alpha_LQSignal_Acceptance_Var3c","value":0.0},{"name":"alpha_LQSignal_Acceptance_scale","value":0.0},{"const":true,"name":"nominalLumi","value":1.0},{"name":"alpha_ATLAS_FTAG_EXTRAP_C","value":0.0},{"name":"alpha_ATLAS_JES_NP_Stat3","value":0.0},{"name":"alpha_ATLAS_JES_NP_Stat4","value":0.0},{"name":"alpha_ATLAS_JES_BJES","value":0.0},{"name":"alpha_ATLAS_JES_EtaInter_Model","value":0.0},{"name":"alpha_ATLAS_JES_EtaInter_Stat","value":0.0},{"name":"alpha_ATLAS_JES_Flavor_Comp","value":0.0},{"name":"alpha_ATLAS_JES_Flavor_Resp","value":0.0},{"name":"alpha_ATLAS_JES_NP_Mod1","value":0.0},{"name":"alpha_ATLAS_JES_PU_OffsetMu","value":0.0},{"name":"alpha_ATLAS_JES_PU_Rho","value":0.0},{"name":"alpha_ATLAS_EG_SCALE","value":0.0},{"name":"alpha_ATLAS_MU_MS","value":0.0},{"name":"alpha_ATLAS_JVT","value":0.0},{"name":"alpha_ATLAS_FTAG_B0","value":0.0},{"name":"alpha_ATLAS_FTAG_B1","value":0.0},{"name":"alpha_ATLAS_FTAG_B3","value":0.0},{"name":"alpha_ATLAS_FTAG_C0","value":0.0},{"name":"alpha_ATLAS_FTAG_C1","value":0.0},{"name":"alpha_ATLAS_JES_NP_Mod4","value":0.0},{"name":"alpha_ATLAS_JES_NP_Stat1","value":0.0},{"name":"alpha_ATLAS_JES_NP_Mix1","value":0.0},{"name":"alpha_ATLAS_JES_NP_Mix2","value":0.0},{"name":"alpha_ATLAS_JES_NP_Mod2","value":0.0},{"name":"alpha_ATLAS_JES_NP_Mod3","value":0.0},{"name":"alpha_ATLAS_JES_PU_OffsetNPV","value":0.0},{"name":"alpha_ATLAS_MET_Perp","value":0.0},{"name":"alpha_ATLAS_MET_Scale","value":0.0},{"name":"alpha_ATLAS_TAU_SF_ELEOLR","value":0.0},{"name":"alpha_ATLAS_TAU_SF_RECO","value":0.0},{"name":"alpha_ATLAS_TAU_SF_RECO_AFII","value":0.0},{"name":"alpha_ATLAS_TAU_SF_RNNID_1PGE40","value":0.0},{"name":"alpha_ATLAS_TAU_SF_RNNID_SYST","value":0.0},{"name":"alpha_ATLAS_TAU_TES_DET_LOWPT_TAU","value":0.0},{"name":"alpha_ATLAS_TRUETAU_RW_STAT","value":0.0},{"name":"alpha_ATLAS_TAU_TES_DET_HIGHPT_TAU_1p","value":0.0},{"name":"alpha_ATLAS_JES_EtaInter_NonClosurePosEta","value":0.0},{"name":"alpha_ATLAS_JES_NP_Det1","value":0.0},{"name":"alpha_ATLAS_JES_PU_PtTerm","value":0.0},{"name":"alpha_ATLAS_TAU_SF_RNNID_1P2530","value":0.0},{"name":"alpha_ATLAS_TAU_SF_RNNID_1P3040","value":0.0},{"name":"alpha_ATLAS_TAU_SF_RNNID_3P2530","value":0.0},{"name":"alpha_ATLAS_TAU_SF_RNNID_3P3040","value":0.0},{"name":"alpha_ATLAS_TAU_SF_RNNID_3PGE40","value":0.0},{"name":"alpha_ATLAS_TAU_SF_TRUEELECTRON_ELEOLR_STAT","value":0.0},{"name":"alpha_ATLAS_TAU_SF_TRUEELECTRON_ELEOLR_SYST","value":0.0},{"name":"alpha_ATLAS_MU_SCALE","value":0.0},{"name":"alpha_ATLAS_MU_RESBIAS","value":0.0},{"name":"alpha_ATLAS_TAU_SF_RNNID_HIGHPT","value":0.0},{"name":"alpha_ATLAS_MET_Para","value":0.0},{"name":"alpha_ATLAS_TAU_TES_DET_HIGHPT_TAU_3p","value":0.0}]},{"name":"NominalParamValues","parameters":[{"const":true,"name":"Lumi","value":1.0},{"name":"SigXsecOverSM","value":0.0},{"name":"alpha_ATLAS_EG_SCALE","value":0.0},{"name":"alpha_ATLAS_EL_SF_ID","value":0.0},{"name":"alpha_ATLAS_FTAG_B0","value":0.0},{"name":"alpha_ATLAS_FTAG_B1","value":0.0},{"name":"alpha_ATLAS_FTAG_B3","value":0.0},{"name":"alpha_ATLAS_FTAG_C0","value":0.0},{"name":"alpha_ATLAS_FTAG_C1","value":0.0},{"name":"alpha_ATLAS_FTAG_EXTRAP_C","value":0.0},{"name":"alpha_ATLAS_JES_BJES","value":0.0},{"name":"alpha_ATLAS_JES_EtaInter_Model","value":0.0},{"name":"alpha_ATLAS_JES_EtaInter_NonClosurePosEta","value":0.0},{"name":"alpha_ATLAS_JES_EtaInter_Stat","value":0.0},{"name":"alpha_ATLAS_JES_Flavor_Comp","value":0.0},{"name":"alpha_ATLAS_JES_Flavor_Resp","value":0.0},{"name":"alpha_ATLAS_JES_NP_Det1","value":0.0},{"name":"alpha_ATLAS_JES_NP_Mix1","value":0.0},{"name":"alpha_ATLAS_JES_NP_Mix2","value":0.0},{"name":"alpha_ATLAS_JES_NP_Mod1","value":0.0},{"name":"alpha_ATLAS_JES_NP_Mod2","value":0.0},{"name":"alpha_ATLAS_JES_NP_Mod3","value":0.0},{"name":"alpha_ATLAS_JES_NP_Mod4","value":0.0},{"name":"alpha_ATLAS_JES_NP_Stat1","value":0.0},{"name":"alpha_ATLAS_JES_NP_Stat3","value":0.0},{"name":"alpha_ATLAS_JES_NP_Stat4","value":0.0},{"name":"alpha_ATLAS_JES_PU_OffsetMu","value":0.0},{"name":"alpha_ATLAS_JES_PU_OffsetNPV","value":0.0},{"name":"alpha_ATLAS_JES_PU_PtTerm","value":0.0},{"name":"alpha_ATLAS_JES_PU_Rho","value":0.0},{"name":"alpha_ATLAS_JVT","value":0.0},{"name":"alpha_ATLAS_MET_Para","value":0.0},{"name":"alpha_ATLAS_MET_Perp","value":0.0},{"name":"alpha_ATLAS_MET_Scale","value":0.0},{"name":"alpha_ATLAS_MU_MS","value":0.0},{"name":"alpha_ATLAS_MU_RESBIAS","value":0.0},{"name":"alpha_ATLAS_MU_SCALE","value":0.0},{"name":"alpha_ATLAS_MU_SF_Isol_Stat","value":0.0},{"name":"alpha_ATLAS_MU_SF_Isol_Syst","value":0.0},{"name":"alpha_ATLAS_PRW_DATASF","value":0.0},{"name":"alpha_ATLAS_TAU_SF_ELEOLR","value":0.0},{"name":"alpha_ATLAS_TAU_SF_RECO","value":0.0},{"name":"alpha_ATLAS_TAU_SF_RECO_AFII","value":0.0},{"name":"alpha_ATLAS_TAU_SF_RNNID_1P2530","value":0.0},{"name":"alpha_ATLAS_TAU_SF_RNNID_1P3040","value":0.0},{"name":"alpha_ATLAS_TAU_SF_RNNID_1PGE40","value":0.0},{"name":"alpha_ATLAS_TAU_SF_RNNID_3P2530","value":0.0},{"name":"alpha_ATLAS_TAU_SF_RNNID_3P3040","value":0.0},{"name":"alpha_ATLAS_TAU_SF_RNNID_3PGE40","value":0.0},{"name":"alpha_ATLAS_TAU_SF_RNNID_HIGHPT","value":0.0},{"name":"alpha_ATLAS_TAU_SF_RNNID_SYST","value":0.0},{"name":"alpha_ATLAS_TAU_SF_TRUEELECTRON_ELEOLR_STAT","value":0.0},{"name":"alpha_ATLAS_TAU_SF_TRUEELECTRON_ELEOLR_SYST","value":0.0},{"name":"alpha_ATLAS_TAU_TES_DET_HIGHPT_TAU_1p","value":0.0},{"name":"alpha_ATLAS_TAU_TES_DET_HIGHPT_TAU_3p","value":0.0},{"name":"alpha_ATLAS_TAU_TES_DET_LOWPT_TAU","value":0.0},{"name":"alpha_ATLAS_TRUETAU_RW_STAT","value":0.0},{"name":"alpha_ATLAS_lumi","value":0.0},{"name":"alpha_LQSignal_Acceptance_PDF_lowmass","value":0.0},{"name":"alpha_LQSignal_Acceptance_Var3c","value":0.0},{"name":"alpha_LQSignal_Acceptance_scale","value":0.0},{"const":true,"name":"nominalLumi","value":1.0}]}]}